{"location": "Pittsburg, CA", "term": "restaurant", "radius": 3768, "businesses": [{"id": "PgjXlKuRGs80vPBvUK5UGg", "alias": "the-waterfront-grill-and-cafe-pittsburg", "name": "The Waterfront Grill & Cafe", "image_url": "https://s3-media3.fl.yelpcdn.com/bphoto/eyMYzzUByqlhmiMye0BGoA/o.jpg", "is_closed": false, "url": "https://www.yelp.com/biz/the-waterfront-grill-and-cafe-pittsburg?adjust_creative=IokN4du3-7NwKcCaUms5LA&utm_campaign=yelp_api_v3&utm_medium=api_v3_business_search&utm_source=IokN4du3-7NwKcCaUms5LA", "review_count": 101, "categories": [{"alias": "tradamerican", "title": "American (Traditional)"}, {"alias": "seafood", "title": "Seafood"}, {"alias": "steak", "title": "Steakhouses"}], "rating": 3.5, "coordinates": {"latitude": 38.0353033463332, "longitude": -121.883522830904}, "transactions": [], "price": "$$", "location": {"address1": "51 Marina Blvd", "address2": "Ste A", "address3": null, "city": "Pittsburg", "zip_code": "94565", "country": "US", "state": "CA", "display_address": ["51 Marina Blvd", "Ste A", "Pittsburg, CA 94565"]}, "phone": "+19252679775", "display_phone": "(925) 267-9775", "distance": 540.8080649012297}, {"id": "omHQI6-Q65ql7JVWElFscQ", "alias": "creasian-bistro-pittsburg", "name": "CreAsian Bistro", "image_url": "https://s3-media4.fl.yelpcdn.com/bphoto/eD9pE6kwUGPeyJaPX2maAg/o.jpg", "is_closed": false, "url": "https://www.yelp.com/biz/creasian-bistro-pittsburg?adjust_creative=IokN4du3-7NwKcCaUms5LA&utm_campaign=yelp_api_v3&utm_medium=api_v3_business_search&utm_source=IokN4du3-7NwKcCaUms5LA", "review_count": 379, "categories": [{"alias": "vietnamese", "title": "Vietnamese"}, {"alias": "asianfusion", "title": "Asian Fusion"}, {"alias": "bars", "title": "Bars"}], "rating": 4.0, "coordinates": {"latitude": 38.03116, "longitude": -121.88406}, "transactions": [], "price": "$$", "location": {"address1": "610 Railroad Ave", "address2": "", "address3": "", "city": "Pittsburg", "zip_code": "94565", "country": "US", "state": "CA", "display_address": ["610 Railroad Ave", "Pittsburg, CA 94565"]}, "phone": "+19252672828", "display_phone": "(925) 267-2828", "distance": 1010.5382142096556}, {"id": "G9fBVf3Jkzf6_WXdZbtaaw", "alias": "blue-saigon-pittsburg", "name": "Blue Saigon", "image_url": "https://s3-media2.fl.yelpcdn.com/bphoto/5N7Dc8F6fjufL2_IbHqhqg/o.jpg", "is_closed": false, "url": "https://www.yelp.com/biz/blue-saigon-pittsburg?adjust_creative=IokN4du3-7NwKcCaUms5LA&utm_campaign=yelp_api_v3&utm_medium=api_v3_business_search&utm_source=IokN4du3-7NwKcCaUms5LA", "review_count": 865, "categories": [{"alias": "asianfusion", "title": "Asian Fusion"}, {"alias": "vietnamese", "title": "Vietnamese"}, {"alias": "filipino", "title": "Filipino"}], "rating": 4.5, "coordinates": {"latitude": 38.0134741, "longitude": -121.8905534}, "transactions": [], "price": "$", "location": {"address1": "2243 Railroad Ave", "address2": "", "address3": "", "city": "Pittsburg", "zip_code": "94565", "country": "US", "state": "CA", "display_address": ["2243 Railroad Ave", "Pittsburg, CA 94565"]}, "phone": "+19252072761", "display_phone": "(925) 207-2761", "distance": 3031.5941703961776}, {"id": "C8n6ysIbd-bdKpPtUWEU0g", "alias": "la-veranda-ristorante-italiano-pittsburg", "name": "La Veranda Ristorante Italiano", "image_url": "https://s3-media3.fl.yelpcdn.com/bphoto/g5jc2mmJ212VoF3VcnvxzA/o.jpg", "is_closed": false, "url": "https://www.yelp.com/biz/la-veranda-ristorante-italiano-pittsburg?adjust_creative=IokN4du3-7NwKcCaUms5LA&utm_campaign=yelp_api_v3&utm_medium=api_v3_business_search&utm_source=IokN4du3-7NwKcCaUms5LA", "review_count": 286, "categories": [{"alias": "italian", "title": "Italian"}], "rating": 4.0, "coordinates": {"latitude": 38.0323041, "longitude": -121.8838656}, "transactions": [], "price": "$$", "location": {"address1": "444 Railroad Ave", "address2": "", "address3": "", "city": "Pittsburg", "zip_code": "94565", "country": "US", "state": "CA", "display_address": ["444 Railroad Ave", "Pittsburg, CA 94565"]}, "phone": "+19254270444", "display_phone": "(925) 427-0444", "distance": 865.938937479018}, {"id": "omGi-gmogVl7jDU1Pzh4yQ", "alias": "skyview-noodle-and-tea-pittsburg-3", "name": "Skyview Noodle & Tea", "image_url": "https://s3-media4.fl.yelpcdn.com/bphoto/ccdw5EO29sCaYUU5vpGzDQ/o.jpg", "is_closed": false, "url": "https://www.yelp.com/biz/skyview-noodle-and-tea-pittsburg-3?adjust_creative=IokN4du3-7NwKcCaUms5LA&utm_campaign=yelp_api_v3&utm_medium=api_v3_business_search&utm_source=IokN4du3-7NwKcCaUms5LA", "review_count": 201, "categories": [{"alias": "noodles", "title": "Noodles"}, {"alias": "bubbletea", "title": "Bubble Tea"}, {"alias": "chinese", "title": "Chinese"}], "rating": 4.5, "coordinates": {"latitude": 38.0329401103613, "longitude": -121.882134117186}, "transactions": ["pickup", "delivery"], "price": "$$", "location": {"address1": "200 E 3rd St", "address2": "", "address3": null, "city": "Pittsburg", "zip_code": "94565", "country": "US", "state": "CA", "display_address": ["200 E 3rd St", "Pittsburg, CA 94565"]}, "phone": "+19253184580", "display_phone": "(925) 318-4580", "distance": 778.9828593044302}, {"id": "sW44_Mjd-f0LG1aeMIG3Mg", "alias": "e-j-phair-brewing-company-pittsburg-pittsburg", "name": "E.J. Phair Brewing Company - Pittsburg", "image_url": "https://s3-media2.fl.yelpcdn.com/bphoto/7Nf4Ss_AqLhCFiSdBK8tkA/o.jpg", "is_closed": false, "url": "https://www.yelp.com/biz/e-j-phair-brewing-company-pittsburg-pittsburg?adjust_creative=IokN4du3-7NwKcCaUms5LA&utm_campaign=yelp_api_v3&utm_medium=api_v3_business_search&utm_source=IokN4du3-7NwKcCaUms5LA", "review_count": 234, "categories": [{"alias": "breweries", "title": "Breweries"}, {"alias": "pizza", "title": "Pizza"}, {"alias": "comedyclubs", "title": "Comedy Clubs"}], "rating": 4.0, "coordinates": {"latitude": 38.03302, "longitude": -121.88251}, "transactions": [], "price": "$$", "location": {"address1": "300 Cumberland St", "address2": "", "address3": "", "city": "Pittsburg", "zip_code": "94565", "country": "US", "state": "CA", "display_address": ["300 Cumberland St", "Pittsburg, CA 94565"]}, "phone": "+19254277204", "display_phone": "(925) 427-7204", "distance": 773.3204839956577}, {"id": "Kj0gDjy-ULRIjgtr64GB5w", "alias": "new-mecca-cafe-pittsburg-2", "name": "New Mecca Cafe", "image_url": "https://s3-media3.fl.yelpcdn.com/bphoto/ygcMaTHoImOJrhILz5n3pA/o.jpg", "is_closed": false, "url": "https://www.yelp.com/biz/new-mecca-cafe-pittsburg-2?adjust_creative=IokN4du3-7NwKcCaUms5LA&utm_campaign=yelp_api_v3&utm_medium=api_v3_business_search&utm_source=IokN4du3-7NwKcCaUms5LA", "review_count": 710, "categories": [{"alias": "mexican", "title": "Mexican"}], "rating": 3.5, "coordinates": {"latitude": 38.03324, "longitude": -121.88371}, "transactions": [], "price": "$$", "location": {"address1": "324 Railroad Ave", "address2": null, "address3": "", "city": "Pittsburg", "zip_code": "94565", "country": "US", "state": "CA", "display_address": ["324 Railroad Ave", "Pittsburg, CA 94565"]}, "phone": "+19254327433", "display_phone": "(925) 432-7433", "distance": 753.3619754978284}, {"id": "HH-9zSAnwCvG2O437uLMAw", "alias": "yummy-hawaiian-bbq-pittsburg", "name": "Yummy Hawaiian BBQ", "image_url": "https://s3-media1.fl.yelpcdn.com/bphoto/eqVLO5U_YoDOAxusJygigQ/o.jpg", "is_closed": false, "url": "https://www.yelp.com/biz/yummy-hawaiian-bbq-pittsburg?adjust_creative=IokN4du3-7NwKcCaUms5LA&utm_campaign=yelp_api_v3&utm_medium=api_v3_business_search&utm_source=IokN4du3-7NwKcCaUms5LA", "review_count": 56, "categories": [{"alias": "bbq", "title": "Barbeque"}, {"alias": "burgers", "title": "Burgers"}, {"alias": "hawaiian", "title": "Hawaiian"}], "rating": 4.5, "coordinates": {"latitude": 38.00749983, "longitude": -121.8915005}, "transactions": [], "price": "$", "location": {"address1": "160 Atlantic Ave", "address2": null, "address3": "", "city": "Pittsburg", "zip_code": "94565", "country": "US", "state": "CA", "display_address": ["160 Atlantic Ave", "Pittsburg, CA 94565"]}, "phone": "+19256353081", "display_phone": "(925) 635-3081", "distance": 3715.959833385822}, {"id": "xquwSsyCYzK0ZZcCmrwcpw", "alias": "just-crackn-pittsburg", "name": "Just Crack'N", "image_url": "https://s3-media1.fl.yelpcdn.com/bphoto/a0aE6O64X2XnKv9gVUaNOQ/o.jpg", "is_closed": false, "url": "https://www.yelp.com/biz/just-crackn-pittsburg?adjust_creative=IokN4du3-7NwKcCaUms5LA&utm_campaign=yelp_api_v3&utm_medium=api_v3_business_search&utm_source=IokN4du3-7NwKcCaUms5LA", "review_count": 109, "categories": [{"alias": "seafood", "title": "Seafood"}, {"alias": "cajun", "title": "Cajun/Creole"}, {"alias": "southern", "title": "Southern"}], "rating": 3.0, "coordinates": {"latitude": 38.0079883, "longitude": -121.8690707}, "transactions": ["delivery", "pickup"], "price": "$$", "location": {"address1": "1291 E Leland Rd", "address2": null, "address3": "", "city": "Pittsburg", "zip_code": "94565", "country": "US", "state": "CA", "display_address": ["1291 E Leland Rd", "Pittsburg, CA 94565"]}, "phone": "+14152512109", "display_phone": "(415) 251-2109", "distance": 3713.101262170735}, {"id": "1AYtaN_felpUClHm7CF7eQ", "alias": "lumpys-diner-pittsburg", "name": "Lumpy's Diner", "image_url": "https://s3-media2.fl.yelpcdn.com/bphoto/85Blc1FUOmDy-9zGijH15A/o.jpg", "is_closed": false, "url": "https://www.yelp.com/biz/lumpys-diner-pittsburg?adjust_creative=IokN4du3-7NwKcCaUms5LA&utm_campaign=yelp_api_v3&utm_medium=api_v3_business_search&utm_source=IokN4du3-7NwKcCaUms5LA", "review_count": 293, "categories": [{"alias": "diners", "title": "Diners"}, {"alias": "burgers", "title": "Burgers"}], "rating": 4.0, "coordinates": {"latitude": 38.0308031793613, "longitude": -121.883728299416}, "transactions": [], "price": "$", "location": {"address1": "615 Railroad Ave", "address2": "", "address3": "", "city": "Pittsburg", "zip_code": "94565", "country": "US", "state": "CA", "display_address": ["615 Railroad Ave", "Pittsburg, CA 94565"]}, "phone": "+19254393911", "display_phone": "(925) 439-3911", "distance": 1031.7616581987256}, {"id": "d082-1Ps_mn9yjOcU7YyLA", "alias": "dads-bbq-pittsburg", "name": "Dad's BBQ", "image_url": "https://s3-media3.fl.yelpcdn.com/bphoto/ycQmmpah6ypn3_t1T4htLg/o.jpg", "is_closed": false, "url": "https://www.yelp.com/biz/dads-bbq-pittsburg?adjust_creative=IokN4du3-7NwKcCaUms5LA&utm_campaign=yelp_api_v3&utm_medium=api_v3_business_search&utm_source=IokN4du3-7NwKcCaUms5LA", "review_count": 230, "categories": [{"alias": "bbq", "title": "Barbeque"}], "rating": 3.5, "coordinates": {"latitude": 38.029678, "longitude": -121.884332}, "transactions": [], "price": "$$", "location": {"address1": "785 Railroad Ave", "address2": null, "address3": "", "city": "Pittsburg", "zip_code": "94565", "country": "US", "state": "CA", "display_address": ["785 Railroad Ave", "Pittsburg, CA 94565"]}, "phone": "+19254391955", "display_phone": "(925) 439-1955", "distance": 1164.655396231376}, {"id": "xxVdF9QtAfETFM549fhN2g", "alias": "tokyo-and-beijing-pittsburg", "name": "Tokyo & Beijing", "image_url": "https://s3-media2.fl.yelpcdn.com/bphoto/7giMFsucF_7ZUW3H1IDfXQ/o.jpg", "is_closed": false, "url": "https://www.yelp.com/biz/tokyo-and-beijing-pittsburg?adjust_creative=IokN4du3-7NwKcCaUms5LA&utm_campaign=yelp_api_v3&utm_medium=api_v3_business_search&utm_source=IokN4du3-7NwKcCaUms5LA", "review_count": 197, "categories": [{"alias": "chinese", "title": "Chinese"}, {"alias": "sushi", "title": "Sushi Bars"}, {"alias": "japanese", "title": "Japanese"}], "rating": 4.0, "coordinates": {"latitude": 38.0135855609323, "longitude": -121.889940381091}, "transactions": [], "price": "$$", "location": {"address1": "2225 Railroad Ave", "address2": "Ste 102", "address3": "", "city": "Pittsburg", "zip_code": "94565", "country": "US", "state": "CA", "display_address": ["2225 Railroad Ave", "Ste 102", "Pittsburg, CA 94565"]}, "phone": "+19254398877", "display_phone": "(925) 439-8877", "distance": 3018.8021208941464}, {"id": "MatIWG08k0gCdCoomM75Og", "alias": "rocky-s-kitchen-pittsburg-2", "name": "Rocky\u2019s Kitchen", "image_url": "https://s3-media2.fl.yelpcdn.com/bphoto/LVt8sCAc4alOnRKqWy-vqw/o.jpg", "is_closed": false, "url": "https://www.yelp.com/biz/rocky-s-kitchen-pittsburg-2?adjust_creative=IokN4du3-7NwKcCaUms5LA&utm_campaign=yelp_api_v3&utm_medium=api_v3_business_search&utm_source=IokN4du3-7NwKcCaUms5LA", "review_count": 16, "categories": [{"alias": "sandwiches", "title": "Sandwiches"}, {"alias": "coffee", "title": "Coffee & Tea"}, {"alias": "breakfast_brunch", "title": "Breakfast & Brunch"}], "rating": 4.5, "coordinates": {"latitude": 38.018804, "longitude": -121.890899}, "transactions": [], "location": {"address1": "1005 Center Dr", "address2": "", "address3": null, "city": "Pittsburg", "zip_code": "94565", "country": "US", "state": "CA", "display_address": ["1005 Center Dr", "Pittsburg, CA 94565"]}, "phone": "+19252672442", "display_phone": "(925) 267-2442", "distance": 2474.5473796428623}, {"id": "Fn-MJViiJUf_xwJuPbZKIw", "alias": "el-buen-gusto-salvadore\u00f1o-pittsburg-3", "name": "El Buen Gusto Salvadore\u00f1o", "image_url": "https://s3-media4.fl.yelpcdn.com/bphoto/CAW6NJ_eMVkjmOB0QsGOgA/o.jpg", "is_closed": false, "url": "https://www.yelp.com/biz/el-buen-gusto-salvadore%C3%B1o-pittsburg-3?adjust_creative=IokN4du3-7NwKcCaUms5LA&utm_campaign=yelp_api_v3&utm_medium=api_v3_business_search&utm_source=IokN4du3-7NwKcCaUms5LA", "review_count": 31, "categories": [{"alias": "salvadoran", "title": "Salvadoran"}], "rating": 4.0, "coordinates": {"latitude": 38.011554231265, "longitude": -121.889811940491}, "transactions": [], "location": {"address1": "136 E Leland Rd", "address2": "", "address3": null, "city": "Pittsburg", "zip_code": "94565", "country": "US", "state": "CA", "display_address": ["136 E Leland Rd", "Pittsburg, CA 94565"]}, "phone": "+19252674763", "display_phone": "(925) 267-4763", "distance": 3235.9746245871793}, {"id": "YKQqD6jsRKa2qBId9GEUZg", "alias": "las-panchitas-pittsburg", "name": "Las Panchitas", "image_url": "https://s3-media3.fl.yelpcdn.com/bphoto/bOrDi_Lz1eHJGig_NsYD5A/o.jpg", "is_closed": false, "url": "https://www.yelp.com/biz/las-panchitas-pittsburg?adjust_creative=IokN4du3-7NwKcCaUms5LA&utm_campaign=yelp_api_v3&utm_medium=api_v3_business_search&utm_source=IokN4du3-7NwKcCaUms5LA", "review_count": 291, "categories": [{"alias": "mexican", "title": "Mexican"}], "rating": 4.0, "coordinates": {"latitude": 38.007715977894, "longitude": -121.870727068344}, "transactions": ["pickup"], "price": "$", "location": {"address1": "1270 E Leland Rd", "address2": "Ste 100", "address3": "", "city": "Pittsburg", "zip_code": "94565", "country": "US", "state": "CA", "display_address": ["1270 E Leland Rd", "Ste 100", "Pittsburg, CA 94565"]}, "phone": "+19254328226", "display_phone": "(925) 432-8226", "distance": 3707.842643173807}, {"id": "l_b8eQUmOsZxd_l4OLhMxQ", "alias": "lunahuan\u00e1-peruvian-buffet-restaurant-pittsburg", "name": "Lunahuan\u00e1 Peruvian Buffet Restaurant", "image_url": "https://s3-media3.fl.yelpcdn.com/bphoto/B6T-Dbecwa3qlRlfSKMVpg/o.jpg", "is_closed": false, "url": "https://www.yelp.com/biz/lunahuan%C3%A1-peruvian-buffet-restaurant-pittsburg?adjust_creative=IokN4du3-7NwKcCaUms5LA&utm_campaign=yelp_api_v3&utm_medium=api_v3_business_search&utm_source=IokN4du3-7NwKcCaUms5LA", "review_count": 47, "categories": [{"alias": "buffets", "title": "Buffets"}, {"alias": "peruvian", "title": "Peruvian"}], "rating": 4.0, "coordinates": {"latitude": 38.008416, "longitude": -121.8860433}, "transactions": [], "price": "$$", "location": {"address1": "2931 Harbor St", "address2": "Ste N", "address3": "", "city": "Pittsburg", "zip_code": "94565", "country": "US", "state": "CA", "display_address": ["2931 Harbor St", "Ste N", "Pittsburg, CA 94565"]}, "phone": "+19252191076", "display_phone": "(925) 219-1076", "distance": 3525.9047273102515}, {"id": "Sil6obqKjER1zPobsypqsg", "alias": "samurai-x-pittsburg", "name": "Samurai X", "image_url": "https://s3-media4.fl.yelpcdn.com/bphoto/X25dxwp7TOleb5U9FNjtuw/o.jpg", "is_closed": false, "url": "https://www.yelp.com/biz/samurai-x-pittsburg?adjust_creative=IokN4du3-7NwKcCaUms5LA&utm_campaign=yelp_api_v3&utm_medium=api_v3_business_search&utm_source=IokN4du3-7NwKcCaUms5LA", "review_count": 253, "categories": [{"alias": "japanese", "title": "Japanese"}, {"alias": "sushi", "title": "Sushi Bars"}], "rating": 4.0, "coordinates": {"latitude": 38.0100611877242, "longitude": -121.868245631203}, "transactions": [], "price": "$$", "location": {"address1": "2171 Loveridge Rd", "address2": "", "address3": "", "city": "Pittsburg", "zip_code": "94565", "country": "US", "state": "CA", "display_address": ["2171 Loveridge Rd", "Pittsburg, CA 94565"]}, "phone": "+19254392000", "display_phone": "(925) 439-2000", "distance": 3522.8221985237424}, {"id": "54PWzGSGaWrGPBBX228hmA", "alias": "golden-bakery-pittsburg", "name": "Golden Bakery", "image_url": "https://s3-media2.fl.yelpcdn.com/bphoto/HnHRzEnPN3mtSgpuEpgIxw/o.jpg", "is_closed": false, "url": "https://www.yelp.com/biz/golden-bakery-pittsburg?adjust_creative=IokN4du3-7NwKcCaUms5LA&utm_campaign=yelp_api_v3&utm_medium=api_v3_business_search&utm_source=IokN4du3-7NwKcCaUms5LA", "review_count": 121, "categories": [{"alias": "bakeries", "title": "Bakeries"}, {"alias": "dimsum", "title": "Dim Sum"}], "rating": 4.0, "coordinates": {"latitude": 38.0136496, "longitude": -121.8904874}, "transactions": [], "price": "$", "location": {"address1": "2229 Railroad Ave", "address2": null, "address3": "", "city": "Pittsburg", "zip_code": "94565", "country": "US", "state": "CA", "display_address": ["2229 Railroad Ave", "Pittsburg, CA 94565"]}, "phone": "+14153193129", "display_phone": "(415) 319-3129", "distance": 3019.440633041211}, {"id": "RsgxKM4y5V_po23Iy3lTww", "alias": "fiya-spice-caribbean-pittsburg", "name": "Fiya Spice Caribbean", "image_url": "https://s3-media1.fl.yelpcdn.com/bphoto/7NBUdJXMLVWdJqIumy-GBg/o.jpg", "is_closed": false, "url": "https://www.yelp.com/biz/fiya-spice-caribbean-pittsburg?adjust_creative=IokN4du3-7NwKcCaUms5LA&utm_campaign=yelp_api_v3&utm_medium=api_v3_business_search&utm_source=IokN4du3-7NwKcCaUms5LA", "review_count": 1, "categories": [{"alias": "foodtrucks", "title": "Food Trucks"}, {"alias": "caribbean", "title": "Caribbean"}, {"alias": "catering", "title": "Caterers"}], "rating": 5.0, "coordinates": {"latitude": 38.011279, "longitude": -121.876098}, "transactions": [], "location": {"address1": "", "address2": null, "address3": "", "city": "Pittsburg", "zip_code": "94565", "country": "US", "state": "CA", "display_address": ["Pittsburg, CA 94565"]}, "phone": "+15106863325", "display_phone": "(510) 686-3325", "distance": 3223.104286382095}, {"id": "roKxrwNSBdrlX1ZaxintNA", "alias": "filipino-turo-turo-pittsburg", "name": "Filipino turo-turo", "image_url": "https://s3-media2.fl.yelpcdn.com/bphoto/uW6fOAkTL4k0aI91a-m9Vg/o.jpg", "is_closed": false, "url": "https://www.yelp.com/biz/filipino-turo-turo-pittsburg?adjust_creative=IokN4du3-7NwKcCaUms5LA&utm_campaign=yelp_api_v3&utm_medium=api_v3_business_search&utm_source=IokN4du3-7NwKcCaUms5LA", "review_count": 6, "categories": [{"alias": "filipino", "title": "Filipino"}], "rating": 4.5, "coordinates": {"latitude": 38.008049278407, "longitude": -121.891876906157}, "transactions": [], "location": {"address1": "155 Atlantic Ave", "address2": "", "address3": "", "city": "Pittsburg", "zip_code": "94565", "country": "US", "state": "CA", "display_address": ["155 Atlantic Ave", "Pittsburg, CA 94565"]}, "phone": "", "display_phone": "", "distance": 3657.1850278470174}, {"id": "t7NATZPGEIIxN1vZT0TSUQ", "alias": "remnant-best-burger-pittsburg-3", "name": "Remnant Best Burger", "image_url": "https://s3-media1.fl.yelpcdn.com/bphoto/fmf23MOcCizSSTPrU93koA/o.jpg", "is_closed": false, "url": "https://www.yelp.com/biz/remnant-best-burger-pittsburg-3?adjust_creative=IokN4du3-7NwKcCaUms5LA&utm_campaign=yelp_api_v3&utm_medium=api_v3_business_search&utm_source=IokN4du3-7NwKcCaUms5LA", "review_count": 103, "categories": [{"alias": "burgers", "title": "Burgers"}], "rating": 4.5, "coordinates": {"latitude": 38.0074255571778, "longitude": -121.886415587559}, "transactions": ["delivery", "pickup"], "price": "$", "location": {"address1": "2941-3033 Harbor St", "address2": "", "address3": null, "city": "Pittsburg", "zip_code": "94565", "country": "US", "state": "CA", "display_address": ["2941-3033 Harbor St", "Pittsburg, CA 94565"]}, "phone": "+19252672992", "display_phone": "(925) 267-2992", "distance": 3639.0016618977397}, {"id": "SWJC6JefbXvEX9TPyeMxvg", "alias": "pho-lee-hoa-phat-pittsburg-5", "name": "Pho Lee Hoa Phat", "image_url": "https://s3-media3.fl.yelpcdn.com/bphoto/0lQX_kG2wSGGvcu6PK-0FQ/o.jpg", "is_closed": false, "url": "https://www.yelp.com/biz/pho-lee-hoa-phat-pittsburg-5?adjust_creative=IokN4du3-7NwKcCaUms5LA&utm_campaign=yelp_api_v3&utm_medium=api_v3_business_search&utm_source=IokN4du3-7NwKcCaUms5LA", "review_count": 138, "categories": [{"alias": "vietnamese", "title": "Vietnamese"}], "rating": 3.0, "coordinates": {"latitude": 38.0114778891118, "longitude": -121.889719069004}, "transactions": [], "price": "$", "location": {"address1": "140 E Leland Rd", "address2": "", "address3": "", "city": "Pittsburg", "zip_code": "94565", "country": "US", "state": "CA", "display_address": ["140 E Leland Rd", "Pittsburg, CA 94565"]}, "phone": "+19252529019", "display_phone": "(925) 252-9019", "distance": 3242.468046117966}, {"id": "J1Hf8UEYBU0k9xFzMdZbug", "alias": "picante-taqueria-pittsburg", "name": "Picante Taqueria", "image_url": "https://s3-media2.fl.yelpcdn.com/bphoto/_DeX96BNEzjBCvXE-81Kgg/o.jpg", "is_closed": false, "url": "https://www.yelp.com/biz/picante-taqueria-pittsburg?adjust_creative=IokN4du3-7NwKcCaUms5LA&utm_campaign=yelp_api_v3&utm_medium=api_v3_business_search&utm_source=IokN4du3-7NwKcCaUms5LA", "review_count": 80, "categories": [{"alias": "mexican", "title": "Mexican"}], "rating": 4.0, "coordinates": {"latitude": 38.01359, "longitude": -121.88993}, "transactions": ["pickup"], "price": "$", "location": {"address1": "2221 Railroad Ave", "address2": "", "address3": "", "city": "Pittsburg", "zip_code": "94565", "country": "US", "state": "CA", "display_address": ["2221 Railroad Ave", "Pittsburg, CA 94565"]}, "phone": "+19254730760", "display_phone": "(925) 473-0760", "distance": 3031.963893820631}, {"id": "BQN6qq6dNf3FGTEYWkwQVQ", "alias": "sunshine-cafe-pittsburg", "name": "Sunshine Cafe", "image_url": "https://s3-media1.fl.yelpcdn.com/bphoto/ry81Nlk4YOm25W6XY6QMuw/o.jpg", "is_closed": false, "url": "https://www.yelp.com/biz/sunshine-cafe-pittsburg?adjust_creative=IokN4du3-7NwKcCaUms5LA&utm_campaign=yelp_api_v3&utm_medium=api_v3_business_search&utm_source=IokN4du3-7NwKcCaUms5LA", "review_count": 77, "categories": [{"alias": "breakfast_brunch", "title": "Breakfast & Brunch"}], "rating": 4.5, "coordinates": {"latitude": 38.0134765912113, "longitude": -121.89040864018}, "transactions": [], "price": "$", "location": {"address1": "2227 Railroad Ave", "address2": "", "address3": null, "city": "Pittsburg", "zip_code": "94565", "country": "US", "state": "CA", "display_address": ["2227 Railroad Ave", "Pittsburg, CA 94565"]}, "phone": "+19252048228", "display_phone": "(925) 204-8228", "distance": 3040.6668480086364}, {"id": "OF1h4QgtQAbpeTeoo-GBbQ", "alias": "nicks-sandwiches-pittsburg", "name": "Nick's Sandwiches", "image_url": "https://s3-media3.fl.yelpcdn.com/bphoto/o0zFWM8BelAbBx0pB1l8MQ/o.jpg", "is_closed": false, "url": "https://www.yelp.com/biz/nicks-sandwiches-pittsburg?adjust_creative=IokN4du3-7NwKcCaUms5LA&utm_campaign=yelp_api_v3&utm_medium=api_v3_business_search&utm_source=IokN4du3-7NwKcCaUms5LA", "review_count": 95, "categories": [{"alias": "sandwiches", "title": "Sandwiches"}, {"alias": "delis", "title": "Delis"}, {"alias": "breakfast_brunch", "title": "Breakfast & Brunch"}], "rating": 4.0, "coordinates": {"latitude": 38.02978, "longitude": -121.88402}, "transactions": ["delivery", "pickup"], "price": "$", "location": {"address1": "765 Railroad Ave", "address2": "", "address3": null, "city": "Pittsburg", "zip_code": "94565", "country": "US", "state": "CA", "display_address": ["765 Railroad Ave", "Pittsburg, CA 94565"]}, "phone": "+19252672722", "display_phone": "(925) 267-2722", "distance": 1144.0242549050984}, {"id": "JKmEh6ayABwGivmZ98ngHg", "alias": "la-hacienda-pittsburg-2", "name": "La Hacienda", "image_url": "https://s3-media2.fl.yelpcdn.com/bphoto/Gylrg53KKgnYb5po-3quKw/o.jpg", "is_closed": false, "url": "https://www.yelp.com/biz/la-hacienda-pittsburg-2?adjust_creative=IokN4du3-7NwKcCaUms5LA&utm_campaign=yelp_api_v3&utm_medium=api_v3_business_search&utm_source=IokN4du3-7NwKcCaUms5LA", "review_count": 52, "categories": [{"alias": "mexican", "title": "Mexican"}, {"alias": "desserts", "title": "Desserts"}], "rating": 4.0, "coordinates": {"latitude": 38.0275995643643, "longitude": -121.88260813373}, "transactions": ["pickup"], "price": "$$", "location": {"address1": "303 E 10th St", "address2": "", "address3": "", "city": "Pittsburg", "zip_code": "94565", "country": "US", "state": "CA", "display_address": ["303 E 10th St", "Pittsburg, CA 94565"]}, "phone": "+19252670018", "display_phone": "(925) 267-0018", "distance": 1374.240529948192}, {"id": "_NUEW2K1olbxxCBxgyV4ZA", "alias": "tacos-barbacoa-pittsburg", "name": "Tacos Barbacoa", "image_url": "https://s3-media3.fl.yelpcdn.com/bphoto/88TfKlOju40ETWvVgjJpSQ/o.jpg", "is_closed": false, "url": "https://www.yelp.com/biz/tacos-barbacoa-pittsburg?adjust_creative=IokN4du3-7NwKcCaUms5LA&utm_campaign=yelp_api_v3&utm_medium=api_v3_business_search&utm_source=IokN4du3-7NwKcCaUms5LA", "review_count": 9, "categories": [{"alias": "tacos", "title": "Tacos"}], "rating": 4.5, "coordinates": {"latitude": 38.0222901955547, "longitude": -121.887597962962}, "transactions": [], "location": {"address1": "1302-1624 Railroad Ave", "address2": "", "address3": null, "city": "Pittsburg", "zip_code": "94565", "country": "US", "state": "CA", "display_address": ["1302-1624 Railroad Ave", "Pittsburg, CA 94565"]}, "phone": "", "display_phone": "", "distance": 2030.2482700329915}, {"id": "QlV8H8E4fB4sG-j6YHn1yA", "alias": "la-pi\u00f1ata-pittsburg-2", "name": "La Pi\u00f1ata", "image_url": "https://s3-media2.fl.yelpcdn.com/bphoto/yR4d47jXoSKGoYh6fNJzBA/o.jpg", "is_closed": false, "url": "https://www.yelp.com/biz/la-pi%C3%B1ata-pittsburg-2?adjust_creative=IokN4du3-7NwKcCaUms5LA&utm_campaign=yelp_api_v3&utm_medium=api_v3_business_search&utm_source=IokN4du3-7NwKcCaUms5LA", "review_count": 269, "categories": [{"alias": "mexican", "title": "Mexican"}], "rating": 3.0, "coordinates": {"latitude": 38.01547, "longitude": -121.88763}, "transactions": [], "price": "$$", "location": {"address1": "95 Bliss Ave", "address2": "", "address3": "", "city": "Pittsburg", "zip_code": "94565", "country": "US", "state": "CA", "display_address": ["95 Bliss Ave", "Pittsburg, CA 94565"]}, "phone": "+19252520222", "display_phone": "(925) 252-0222", "distance": 2765.0926292526633}, {"id": "MkXAlvYEv6aEYXdZex8UnA", "alias": "chicagos-pizza-with-a-twist-pittsburg", "name": "Chicago's Pizza With A Twist", "image_url": "https://s3-media1.fl.yelpcdn.com/bphoto/KW_tpIPYd7fpKYRayQAL6A/o.jpg", "is_closed": false, "url": "https://www.yelp.com/biz/chicagos-pizza-with-a-twist-pittsburg?adjust_creative=IokN4du3-7NwKcCaUms5LA&utm_campaign=yelp_api_v3&utm_medium=api_v3_business_search&utm_source=IokN4du3-7NwKcCaUms5LA", "review_count": 81, "categories": [{"alias": "pizza", "title": "Pizza"}, {"alias": "vegan", "title": "Vegan"}, {"alias": "gluten_free", "title": "Gluten-Free"}], "rating": 4.0, "coordinates": {"latitude": 38.0083725658123, "longitude": -121.891348915857}, "transactions": ["delivery", "pickup"], "price": "$$", "location": {"address1": "2961 Railroad Ave", "address2": "", "address3": null, "city": "Pittsburg", "zip_code": "94565", "country": "US", "state": "CA", "display_address": ["2961 Railroad Ave", "Pittsburg, CA 94565"]}, "phone": "+19254739000", "display_phone": "(925) 473-9000", "distance": 3611.171899321173}, {"id": "utZeFahZjElykcdRZ_NGyA", "alias": "el-buen-gusto-salvadore\u00f1o-pittsburg", "name": "El Buen Gusto Salvadore\u00f1o", "image_url": "https://s3-media2.fl.yelpcdn.com/bphoto/xYv_RxOka9XIOrk-4qQAig/o.jpg", "is_closed": false, "url": "https://www.yelp.com/biz/el-buen-gusto-salvadore%C3%B1o-pittsburg?adjust_creative=IokN4du3-7NwKcCaUms5LA&utm_campaign=yelp_api_v3&utm_medium=api_v3_business_search&utm_source=IokN4du3-7NwKcCaUms5LA", "review_count": 28, "categories": [{"alias": "salvadoran", "title": "Salvadoran"}], "rating": 4.5, "coordinates": {"latitude": 38.011636, "longitude": -121.889886}, "transactions": [], "price": "$", "location": {"address1": "136 E Leland Rd", "address2": "", "address3": null, "city": "Pittsburg", "zip_code": "94565", "country": "US", "state": "CA", "display_address": ["136 E Leland Rd", "Pittsburg, CA 94565"]}, "phone": "+19252674763", "display_phone": "(925) 267-4763", "distance": 3228.553757322162}, {"id": "3p01EKnYeX2fSr_82zrhIg", "alias": "wah-sing-chinese-restaurant-pittsburg", "name": "Wah Sing Chinese Restaurant", "image_url": "https://s3-media1.fl.yelpcdn.com/bphoto/sifYUU2BoBo6OEPAaQWYLg/o.jpg", "is_closed": false, "url": "https://www.yelp.com/biz/wah-sing-chinese-restaurant-pittsburg?adjust_creative=IokN4du3-7NwKcCaUms5LA&utm_campaign=yelp_api_v3&utm_medium=api_v3_business_search&utm_source=IokN4du3-7NwKcCaUms5LA", "review_count": 128, "categories": [{"alias": "chinese", "title": "Chinese"}], "rating": 3.5, "coordinates": {"latitude": 38.01344, "longitude": -121.89131}, "transactions": [], "price": "$$", "location": {"address1": "2222 Railroad Ave", "address2": "", "address3": "", "city": "Pittsburg", "zip_code": "94565", "country": "US", "state": "CA", "display_address": ["2222 Railroad Ave", "Pittsburg, CA 94565"]}, "phone": "+19254391992", "display_phone": "(925) 439-1992", "distance": 3063.6568265080214}, {"id": "5XcQEGjvcu4PS4aNjsUqYA", "alias": "restaurante-mi-salvador-pittsburg", "name": "Restaurante Mi Salvador", "image_url": "https://s3-media3.fl.yelpcdn.com/bphoto/JyKvZyGF2NJnm8eent6Lfw/o.jpg", "is_closed": false, "url": "https://www.yelp.com/biz/restaurante-mi-salvador-pittsburg?adjust_creative=IokN4du3-7NwKcCaUms5LA&utm_campaign=yelp_api_v3&utm_medium=api_v3_business_search&utm_source=IokN4du3-7NwKcCaUms5LA", "review_count": 111, "categories": [{"alias": "salvadoran", "title": "Salvadoran"}], "rating": 3.5, "coordinates": {"latitude": 38.00939, "longitude": -121.891456}, "transactions": [], "price": "$$", "location": {"address1": "2909 Railroad Ave", "address2": "", "address3": null, "city": "Pittsburg", "zip_code": "94565", "country": "US", "state": "CA", "display_address": ["2909 Railroad Ave", "Pittsburg, CA 94565"]}, "phone": "+19254731703", "display_phone": "(925) 473-1703", "distance": 3503.6127868725575}, {"id": "BCgkdfaUBi1TYj6F2sJh_A", "alias": "el-taco-bronco-taco-truck-pittsburg-2", "name": "El Taco Bronco Taco Truck", "image_url": "https://s3-media3.fl.yelpcdn.com/bphoto/YcHu0XXWjXlG6threVBpXA/o.jpg", "is_closed": false, "url": "https://www.yelp.com/biz/el-taco-bronco-taco-truck-pittsburg-2?adjust_creative=IokN4du3-7NwKcCaUms5LA&utm_campaign=yelp_api_v3&utm_medium=api_v3_business_search&utm_source=IokN4du3-7NwKcCaUms5LA", "review_count": 5, "categories": [{"alias": "foodtrucks", "title": "Food Trucks"}, {"alias": "tacos", "title": "Tacos"}], "rating": 3.5, "coordinates": {"latitude": 38.0150912281211, "longitude": -121.878802508158}, "transactions": [], "price": "$", "location": {"address1": null, "address2": null, "address3": null, "city": "Pittsburg", "zip_code": "94565", "country": "US", "state": "CA", "display_address": ["Pittsburg, CA 94565"]}, "phone": "+19255954352", "display_phone": "(925) 595-4352", "distance": 2773.60963636476}, {"id": "VqUYk3c3sd5DdvtJdkaz4g", "alias": "cardenas-markets-pittsburg", "name": "Cardenas Markets", "image_url": "https://s3-media1.fl.yelpcdn.com/bphoto/_FE7Ow24KrcAbodBHVy0Hg/o.jpg", "is_closed": false, "url": "https://www.yelp.com/biz/cardenas-markets-pittsburg?adjust_creative=IokN4du3-7NwKcCaUms5LA&utm_campaign=yelp_api_v3&utm_medium=api_v3_business_search&utm_source=IokN4du3-7NwKcCaUms5LA", "review_count": 238, "categories": [{"alias": "grocery", "title": "Grocery"}, {"alias": "meats", "title": "Meat Shops"}, {"alias": "mexican", "title": "Mexican"}], "rating": 3.5, "coordinates": {"latitude": 38.01632, "longitude": -121.89121}, "transactions": [], "price": "$$", "location": {"address1": "2100 Railroad Ave", "address2": "", "address3": "", "city": "Pittsburg", "zip_code": "94565", "country": "US", "state": "CA", "display_address": ["2100 Railroad Ave", "Pittsburg, CA 94565"]}, "phone": "+19254271697", "display_phone": "(925) 427-1697", "distance": 2764.350676740548}, {"id": "pu9jbinUQ5hfvQdA_rJsLg", "alias": "taqueria-acatlan-pittsburg-2", "name": "Taqueria Acatlan", "image_url": "https://s3-media2.fl.yelpcdn.com/bphoto/iRbVu2Av4jXlsHyxOVrjew/o.jpg", "is_closed": false, "url": "https://www.yelp.com/biz/taqueria-acatlan-pittsburg-2?adjust_creative=IokN4du3-7NwKcCaUms5LA&utm_campaign=yelp_api_v3&utm_medium=api_v3_business_search&utm_source=IokN4du3-7NwKcCaUms5LA", "review_count": 10, "categories": [{"alias": "tacos", "title": "Tacos"}], "rating": 4.0, "coordinates": {"latitude": 38.0222139565885, "longitude": -121.887643333333}, "transactions": [], "location": {"address1": "1390 Railroad Ave", "address2": "", "address3": null, "city": "Pittsburg", "zip_code": "94565", "country": "US", "state": "CA", "display_address": ["1390 Railroad Ave", "Pittsburg, CA 94565"]}, "phone": "", "display_phone": "", "distance": 2039.4631420172468}, {"id": "XjIFEJkDKcWYK9IoYGgT5g", "alias": "asian-express-pittsburg", "name": "Asian Express", "image_url": "https://s3-media2.fl.yelpcdn.com/bphoto/Hz2mATDCRyL9SZ3XU2OwVA/o.jpg", "is_closed": false, "url": "https://www.yelp.com/biz/asian-express-pittsburg?adjust_creative=IokN4du3-7NwKcCaUms5LA&utm_campaign=yelp_api_v3&utm_medium=api_v3_business_search&utm_source=IokN4du3-7NwKcCaUms5LA", "review_count": 36, "categories": [{"alias": "asianfusion", "title": "Asian Fusion"}], "rating": 3.5, "coordinates": {"latitude": 38.0070562484119, "longitude": -121.890699416399}, "transactions": [], "price": "$", "location": {"address1": "184 Atlantic Ave", "address2": "", "address3": "", "city": "Pittsburg", "zip_code": "94565", "country": "US", "state": "CA", "display_address": ["184 Atlantic Ave", "Pittsburg, CA 94565"]}, "phone": "+19252521668", "display_phone": "(925) 252-1668", "distance": 3741.0977777511202}, {"id": "3oNoFql9-k_nQs6zBHtqYQ", "alias": "jade-house-pittsburg", "name": "Jade House", "image_url": "https://s3-media3.fl.yelpcdn.com/bphoto/FqKl69eAWLNtszdLpI8rHQ/o.jpg", "is_closed": false, "url": "https://www.yelp.com/biz/jade-house-pittsburg?adjust_creative=IokN4du3-7NwKcCaUms5LA&utm_campaign=yelp_api_v3&utm_medium=api_v3_business_search&utm_source=IokN4du3-7NwKcCaUms5LA", "review_count": 128, "categories": [{"alias": "chinese", "title": "Chinese"}], "rating": 3.5, "coordinates": {"latitude": 38.008415222168, "longitude": -121.886177062988}, "transactions": [], "price": "$", "location": {"address1": "2931 Harbor St", "address2": "Ste L", "address3": "", "city": "Pittsburg", "zip_code": "94565", "country": "US", "state": "CA", "display_address": ["2931 Harbor St", "Ste L", "Pittsburg, CA 94565"]}, "phone": "+19254320888", "display_phone": "(925) 432-0888", "distance": 3525.9047273102515}, {"id": "txmPK2BkPi71Je3zNkH6CQ", "alias": "taqueria-carnitas-tijuana-pittsburg", "name": "Taqueria Carnitas Tijuana", "image_url": "https://s3-media3.fl.yelpcdn.com/bphoto/rz52LoOKSZaW-F2Hoe8vsQ/o.jpg", "is_closed": false, "url": "https://www.yelp.com/biz/taqueria-carnitas-tijuana-pittsburg?adjust_creative=IokN4du3-7NwKcCaUms5LA&utm_campaign=yelp_api_v3&utm_medium=api_v3_business_search&utm_source=IokN4du3-7NwKcCaUms5LA", "review_count": 176, "categories": [{"alias": "mexican", "title": "Mexican"}], "rating": 3.5, "coordinates": {"latitude": 38.0141, "longitude": -121.88974}, "transactions": [], "price": "$", "location": {"address1": "2193 Railroad Ave", "address2": "", "address3": "", "city": "Pittsburg", "zip_code": "94565", "country": "US", "state": "CA", "display_address": ["2193 Railroad Ave", "Pittsburg, CA 94565"]}, "phone": "+19254393663", "display_phone": "(925) 439-3663", "distance": 2948.0993236568534}, {"id": "xZuQtfnqcKb9wQtD1PMgPw", "alias": "el-chico-pittsburg", "name": "El Chico", "image_url": "https://s3-media4.fl.yelpcdn.com/bphoto/ZB4Xy4cvsv466D8ikJW5Pg/o.jpg", "is_closed": false, "url": "https://www.yelp.com/biz/el-chico-pittsburg?adjust_creative=IokN4du3-7NwKcCaUms5LA&utm_campaign=yelp_api_v3&utm_medium=api_v3_business_search&utm_source=IokN4du3-7NwKcCaUms5LA", "review_count": 52, "categories": [{"alias": "seafood", "title": "Seafood"}, {"alias": "mexican", "title": "Mexican"}], "rating": 3.5, "coordinates": {"latitude": 38.0080482, "longitude": -121.8914992}, "transactions": [], "price": "$$", "location": {"address1": "149 Atlantic Ave", "address2": "", "address3": "", "city": "Pittsburg", "zip_code": "94565", "country": "US", "state": "CA", "display_address": ["149 Atlantic Ave", "Pittsburg, CA 94565"]}, "phone": "+19252520515", "display_phone": "(925) 252-0515", "distance": 3620.6770041187674}, {"id": "xbjvLbp9lLScDtPfM4Stcw", "alias": "all-star-tamales-pittsburg", "name": "All Star Tamales", "image_url": "https://s3-media3.fl.yelpcdn.com/bphoto/_2goyaA5dV-blEzAdfveCg/o.jpg", "is_closed": false, "url": "https://www.yelp.com/biz/all-star-tamales-pittsburg?adjust_creative=IokN4du3-7NwKcCaUms5LA&utm_campaign=yelp_api_v3&utm_medium=api_v3_business_search&utm_source=IokN4du3-7NwKcCaUms5LA", "review_count": 95, "categories": [{"alias": "mexican", "title": "Mexican"}, {"alias": "foodstands", "title": "Food Stands"}], "rating": 4.0, "coordinates": {"latitude": 38.014318, "longitude": -121.888781}, "transactions": [], "price": "$", "location": {"address1": "510 Garcia Ave", "address2": "", "address3": "", "city": "Pittsburg", "zip_code": "94565", "country": "US", "state": "CA", "display_address": ["510 Garcia Ave", "Pittsburg, CA 94565"]}, "phone": "+19252521097", "display_phone": "(925) 252-1097", "distance": 2916.376056887849}, {"id": "V6Nwt9OSCP-gstHhi-ApMQ", "alias": "e-and-g-chinese-cuisine-pittsburg", "name": "E & G Chinese Cuisine", "image_url": "https://s3-media4.fl.yelpcdn.com/bphoto/tlbtxnKwjnn8pp4479QeOA/o.jpg", "is_closed": false, "url": "https://www.yelp.com/biz/e-and-g-chinese-cuisine-pittsburg?adjust_creative=IokN4du3-7NwKcCaUms5LA&utm_campaign=yelp_api_v3&utm_medium=api_v3_business_search&utm_source=IokN4du3-7NwKcCaUms5LA", "review_count": 41, "categories": [{"alias": "chinese", "title": "Chinese"}], "rating": 3.5, "coordinates": {"latitude": 38.01039, "longitude": -121.868542}, "transactions": ["pickup"], "price": "$", "location": {"address1": "2141 Loveridge Rd", "address2": "", "address3": "", "city": "Pittsburg", "zip_code": "94565", "country": "US", "state": "CA", "display_address": ["2141 Loveridge Rd", "Pittsburg, CA 94565"]}, "phone": "+19254398686", "display_phone": "(925) 439-8686", "distance": 3479.7232303340534}, {"id": "PqAkNulkZScBWkY39wp7iQ", "alias": "mountain-mikes-pizza-pittsburg", "name": "Mountain Mike's Pizza", "image_url": "https://s3-media1.fl.yelpcdn.com/bphoto/abzGRJo2OGrfpeZbofMJSA/o.jpg", "is_closed": false, "url": "https://www.yelp.com/biz/mountain-mikes-pizza-pittsburg?adjust_creative=IokN4du3-7NwKcCaUms5LA&utm_campaign=yelp_api_v3&utm_medium=api_v3_business_search&utm_source=IokN4du3-7NwKcCaUms5LA", "review_count": 65, "categories": [{"alias": "pizza", "title": "Pizza"}], "rating": 3.0, "coordinates": {"latitude": 38.0074422, "longitude": -121.8874915}, "transactions": ["delivery", "pickup"], "price": "$$", "location": {"address1": "378 Atlantic Avenue", "address2": "", "address3": "", "city": "Pittsburg", "zip_code": "94565", "country": "US", "state": "CA", "display_address": ["378 Atlantic Avenue", "Pittsburg, CA 94565"]}, "phone": "+19254274700", "display_phone": "(925) 427-4700", "distance": 3649.20900973413}, {"id": "AvAfRVFLMeLd5ih0YlfjVw", "alias": "country-skillets-pittsburg-4", "name": "Country Skillets", "image_url": "https://s3-media4.fl.yelpcdn.com/bphoto/7DhiczS5KBC_TywWccQxBA/o.jpg", "is_closed": false, "url": "https://www.yelp.com/biz/country-skillets-pittsburg-4?adjust_creative=IokN4du3-7NwKcCaUms5LA&utm_campaign=yelp_api_v3&utm_medium=api_v3_business_search&utm_source=IokN4du3-7NwKcCaUms5LA", "review_count": 168, "categories": [{"alias": "breakfast_brunch", "title": "Breakfast & Brunch"}, {"alias": "tradamerican", "title": "American (Traditional)"}], "rating": 3.5, "coordinates": {"latitude": 38.0080280240964, "longitude": -121.886598440258}, "transactions": ["delivery", "pickup"], "price": "$$", "location": {"address1": "2921 Harbor St", "address2": "", "address3": "", "city": "Pittsburg", "zip_code": "94565", "country": "US", "state": "CA", "display_address": ["2921 Harbor St", "Pittsburg, CA 94565"]}, "phone": "+19252520848", "display_phone": "(925) 252-0848", "distance": 3574.374935430762}, {"id": "etfYlixuOyDdkQNomK1ENg", "alias": "island-pacific-supermarket-pittsburg", "name": "Island Pacific Supermarket", "image_url": "https://s3-media3.fl.yelpcdn.com/bphoto/5enjRuQhWxVZ-jQ9VMmDeQ/o.jpg", "is_closed": false, "url": "https://www.yelp.com/biz/island-pacific-supermarket-pittsburg?adjust_creative=IokN4du3-7NwKcCaUms5LA&utm_campaign=yelp_api_v3&utm_medium=api_v3_business_search&utm_source=IokN4du3-7NwKcCaUms5LA", "review_count": 65, "categories": [{"alias": "grocery", "title": "Grocery"}, {"alias": "filipino", "title": "Filipino"}, {"alias": "seafoodmarkets", "title": "Seafood Markets"}], "rating": 2.5, "coordinates": {"latitude": 38.0113996085066, "longitude": -121.860816478832}, "transactions": [], "price": "$$", "location": {"address1": "2100 North Park Blvd", "address2": "", "address3": "", "city": "Pittsburg", "zip_code": "94565", "country": "US", "state": "CA", "display_address": ["2100 North Park Blvd", "Pittsburg, CA 94565"]}, "phone": "+19253182222", "display_phone": "(925) 318-2222", "distance": 3659.7515948715945}, {"id": "G7SbDKJCKL-dGLdRr41ADw", "alias": "philhouse-pittsburg", "name": "PhilHouse", "image_url": "https://s3-media3.fl.yelpcdn.com/bphoto/GHP2XsI1-E0f2hPxch_Ryg/o.jpg", "is_closed": false, "url": "https://www.yelp.com/biz/philhouse-pittsburg?adjust_creative=IokN4du3-7NwKcCaUms5LA&utm_campaign=yelp_api_v3&utm_medium=api_v3_business_search&utm_source=IokN4du3-7NwKcCaUms5LA", "review_count": 5, "categories": [{"alias": "filipino", "title": "Filipino"}], "rating": 2.5, "coordinates": {"latitude": 38.0113704230583, "longitude": -121.860625666059}, "transactions": [], "location": {"address1": "2100 N Park Blvd", "address2": null, "address3": null, "city": "Pittsburg", "zip_code": "94565", "country": "US", "state": "CA", "display_address": ["2100 N Park Blvd", "Pittsburg, CA 94565"]}, "phone": "+19254730804", "display_phone": "(925) 473-0804", "distance": 3670.9168767463916}, {"id": "_wVdXK4a2xjS46zA_QgZQw", "alias": "old-town-pittsburg-pittsburg", "name": "Old Town Pittsburg", "image_url": "https://s3-media2.fl.yelpcdn.com/bphoto/bmOeXpjVft4UkzpNIDammg/o.jpg", "is_closed": false, "url": "https://www.yelp.com/biz/old-town-pittsburg-pittsburg?adjust_creative=IokN4du3-7NwKcCaUms5LA&utm_campaign=yelp_api_v3&utm_medium=api_v3_business_search&utm_source=IokN4du3-7NwKcCaUms5LA", "review_count": 3, "categories": [{"alias": "shopping", "title": "Shopping"}, {"alias": "localflavor", "title": "Local Flavor"}, {"alias": "newamerican", "title": "American (New)"}], "rating": 3.5, "coordinates": {"latitude": 38.032408, "longitude": -121.885815}, "transactions": [], "price": "$", "location": {"address1": "", "address2": "", "address3": "", "city": "Pittsburg", "zip_code": "94565", "country": "US", "state": "CA", "display_address": ["Pittsburg, CA 94565"]}, "phone": "", "display_phone": "", "distance": 913.4073803913069}, {"id": "I-7CQLRkbfO7Ku8pwFk5_Q", "alias": "sonic-drive-in-pittsburg-6", "name": "Sonic Drive-In", "image_url": "https://s3-media1.fl.yelpcdn.com/bphoto/U9PUhrxHJ3jHvFuMnqAzyA/o.jpg", "is_closed": false, "url": "https://www.yelp.com/biz/sonic-drive-in-pittsburg-6?adjust_creative=IokN4du3-7NwKcCaUms5LA&utm_campaign=yelp_api_v3&utm_medium=api_v3_business_search&utm_source=IokN4du3-7NwKcCaUms5LA", "review_count": 331, "categories": [{"alias": "hotdogs", "title": "Fast Food"}, {"alias": "burgers", "title": "Burgers"}, {"alias": "icecream", "title": "Ice Cream & Frozen Yogurt"}], "rating": 1.5, "coordinates": {"latitude": 38.0118768, "longitude": -121.864741}, "transactions": [], "price": "$", "location": {"address1": "1400 N Park Blvd", "address2": null, "address3": null, "city": "Pittsburg", "zip_code": "94565", "country": "US", "state": "CA", "display_address": ["1400 N Park Blvd", "Pittsburg, CA 94565"]}, "phone": "+19252529940", "display_phone": "(925) 252-9940", "distance": 3453.1389571891423}, {"id": "Z9fdaBrJhk6_v6riBkAa-Q", "alias": "popeyes-louisiana-kitchen-pittsburg", "name": "Popeyes Louisiana Kitchen", "image_url": "https://s3-media4.fl.yelpcdn.com/bphoto/Oy_BCgGk0S0-tyj60UMnSg/o.jpg", "is_closed": false, "url": "https://www.yelp.com/biz/popeyes-louisiana-kitchen-pittsburg?adjust_creative=IokN4du3-7NwKcCaUms5LA&utm_campaign=yelp_api_v3&utm_medium=api_v3_business_search&utm_source=IokN4du3-7NwKcCaUms5LA", "review_count": 162, "categories": [{"alias": "hotdogs", "title": "Fast Food"}, {"alias": "chicken_wings", "title": "Chicken Wings"}], "rating": 1.5, "coordinates": {"latitude": 38.0081916802417, "longitude": -121.869627451555}, "transactions": ["delivery", "pickup"], "price": "$", "location": {"address1": "1283 E Leland Rd", "address2": "", "address3": "", "city": "Pittsburg", "zip_code": "94565", "country": "US", "state": "CA", "display_address": ["1283 E Leland Rd", "Pittsburg, CA 94565"]}, "phone": "+19252529888", "display_phone": "(925) 252-9888", "distance": 3683.1056813951427}, {"id": "7jBx1yne86A0oN-GAEXN_w", "alias": "panda-express-pittsburg", "name": "Panda Express", "image_url": "https://s3-media2.fl.yelpcdn.com/bphoto/ZYXesXWxyzVxGB0QbTeAFA/o.jpg", "is_closed": false, "url": "https://www.yelp.com/biz/panda-express-pittsburg?adjust_creative=IokN4du3-7NwKcCaUms5LA&utm_campaign=yelp_api_v3&utm_medium=api_v3_business_search&utm_source=IokN4du3-7NwKcCaUms5LA", "review_count": 78, "categories": [{"alias": "chinese", "title": "Chinese"}, {"alias": "hotdogs", "title": "Fast Food"}], "rating": 2.5, "coordinates": {"latitude": 38.01563398439, "longitude": -121.890533796077}, "transactions": [], "price": "$", "location": {"address1": "2120 Railroad Ave", "address2": "", "address3": "", "city": "Pittsburg", "zip_code": "94565", "country": "US", "state": "CA", "display_address": ["2120 Railroad Ave", "Pittsburg, CA 94565"]}, "phone": "+19254391622", "display_phone": "(925) 439-1622", "distance": 2812.2279418079665}, {"id": "-1mmvnRYIMk79bV4JHmKvQ", "alias": "antojitos-jalisco-snack-pittsburg", "name": "Antojitos Jalisco Snack", "image_url": "https://s3-media4.fl.yelpcdn.com/bphoto/GrILwO_aen_vAjTHXzSI7A/o.jpg", "is_closed": false, "url": "https://www.yelp.com/biz/antojitos-jalisco-snack-pittsburg?adjust_creative=IokN4du3-7NwKcCaUms5LA&utm_campaign=yelp_api_v3&utm_medium=api_v3_business_search&utm_source=IokN4du3-7NwKcCaUms5LA", "review_count": 21, "categories": [{"alias": "mexican", "title": "Mexican"}], "rating": 3.5, "coordinates": {"latitude": 38.0078516589917, "longitude": -121.887805621448}, "transactions": [], "price": "$", "location": {"address1": "418 Atlantic Ave", "address2": "", "address3": "", "city": "Pittsburg", "zip_code": "94565", "country": "US", "state": "CA", "display_address": ["418 Atlantic Ave", "Pittsburg, CA 94565"]}, "phone": "+19254310119", "display_phone": "(925) 431-0119", "distance": 3608.1539458837074}, {"id": "yJcNvmnrccZ8VeD62UdrTA", "alias": "angelos-pizza-and-wings-and-mini-market-pittsburg", "name": "Angelo's Pizza & Wings & Mini Market", "image_url": "https://s3-media3.fl.yelpcdn.com/bphoto/uxJDNLPWj3epMTY1wrds8w/o.jpg", "is_closed": false, "url": "https://www.yelp.com/biz/angelos-pizza-and-wings-and-mini-market-pittsburg?adjust_creative=IokN4du3-7NwKcCaUms5LA&utm_campaign=yelp_api_v3&utm_medium=api_v3_business_search&utm_source=IokN4du3-7NwKcCaUms5LA", "review_count": 11, "categories": [{"alias": "chicken_wings", "title": "Chicken Wings"}, {"alias": "pizza", "title": "Pizza"}], "rating": 3.5, "coordinates": {"latitude": 38.0178713, "longitude": -121.8823485}, "transactions": [], "price": "$", "location": {"address1": "114 Army St", "address2": "", "address3": "", "city": "Pittsburg", "zip_code": "94565", "country": "US", "state": "CA", "display_address": ["114 Army St", "Pittsburg, CA 94565"]}, "phone": "+19254399999", "display_phone": "(925) 439-9999", "distance": 2454.1315844685378}, {"id": "UL8mxHpd9-n0YwRsbDO4Yw", "alias": "togo-s-sandwiches-pittsburg", "name": "Togo\u2019s Sandwiches", "image_url": "https://s3-media3.fl.yelpcdn.com/bphoto/NcEkCzQQvXrfb7rnKpAQNw/o.jpg", "is_closed": false, "url": "https://www.yelp.com/biz/togo-s-sandwiches-pittsburg?adjust_creative=IokN4du3-7NwKcCaUms5LA&utm_campaign=yelp_api_v3&utm_medium=api_v3_business_search&utm_source=IokN4du3-7NwKcCaUms5LA", "review_count": 39, "categories": [{"alias": "sandwiches", "title": "Sandwiches"}, {"alias": "delis", "title": "Delis"}, {"alias": "hotdogs", "title": "Fast Food"}], "rating": 3.0, "coordinates": {"latitude": 38.0152161, "longitude": -121.8903266}, "transactions": [], "price": "$", "location": {"address1": "2130 Railroad Ave", "address2": "", "address3": "", "city": "Pittsburg", "zip_code": "94565", "country": "US", "state": "CA", "display_address": ["2130 Railroad Ave", "Pittsburg, CA 94565"]}, "phone": "+19254399500", "display_phone": "(925) 439-9500", "distance": 2913.2321925428464}, {"id": "I7Svc97Saku3wv4HVrUN4Q", "alias": "19th-pub-and-grille-pittsburg", "name": "19th Pub and Grille", "image_url": "https://s3-media2.fl.yelpcdn.com/bphoto/7j7BLSdFTRa11aHEAFEd9A/o.jpg", "is_closed": false, "url": "https://www.yelp.com/biz/19th-pub-and-grille-pittsburg?adjust_creative=IokN4du3-7NwKcCaUms5LA&utm_campaign=yelp_api_v3&utm_medium=api_v3_business_search&utm_source=IokN4du3-7NwKcCaUms5LA", "review_count": 1, "categories": [{"alias": "tradamerican", "title": "American (Traditional)"}, {"alias": "beer_and_wine", "title": "Beer, Wine & Spirits"}], "rating": 3.0, "coordinates": {"latitude": 38.0142381, "longitude": -121.9118375}, "transactions": [], "location": {"address1": "2242 Golf Club Rd", "address2": "", "address3": "", "city": "Pittsburg", "zip_code": "94565", "country": "US", "state": "CA", "display_address": ["2242 Golf Club Rd", "Pittsburg, CA 94565"]}, "phone": "", "display_phone": "", "distance": 3893.7843253429614}, {"id": "_5s6Qy5at2DJsbmV2Xwqsg", "alias": "kfc-pittsburg-4", "name": "KFC", "image_url": "https://s3-media3.fl.yelpcdn.com/bphoto/YNxU8-rYMjScdhiON0YCWw/o.jpg", "is_closed": false, "url": "https://www.yelp.com/biz/kfc-pittsburg-4?adjust_creative=IokN4du3-7NwKcCaUms5LA&utm_campaign=yelp_api_v3&utm_medium=api_v3_business_search&utm_source=IokN4du3-7NwKcCaUms5LA", "review_count": 128, "categories": [{"alias": "hotdogs", "title": "Fast Food"}, {"alias": "chicken_wings", "title": "Chicken Wings"}, {"alias": "chickenshop", "title": "Chicken Shop"}], "rating": 1.5, "coordinates": {"latitude": 38.0147347200864, "longitude": -121.889787}, "transactions": ["pickup", "delivery"], "price": "$", "location": {"address1": "2155 Railroad Ave", "address2": "", "address3": "", "city": "Pittsburg", "zip_code": "94565", "country": "US", "state": "CA", "display_address": ["2155 Railroad Ave", "Pittsburg, CA 94565"]}, "phone": "+19254392101", "display_phone": "(925) 439-2101", "distance": 2891.6014843065254}, {"id": "mPfNOxVpi0jk_s8RBJlbqQ", "alias": "little-caesars-pizza-pittsburg", "name": "Little Caesars Pizza", "image_url": "https://s3-media2.fl.yelpcdn.com/bphoto/w4ETbC5BkRJbFY1qtjTKuA/o.jpg", "is_closed": false, "url": "https://www.yelp.com/biz/little-caesars-pizza-pittsburg?adjust_creative=IokN4du3-7NwKcCaUms5LA&utm_campaign=yelp_api_v3&utm_medium=api_v3_business_search&utm_source=IokN4du3-7NwKcCaUms5LA", "review_count": 21, "categories": [{"alias": "pizza", "title": "Pizza"}], "rating": 2.5, "coordinates": {"latitude": 38.0078063160181, "longitude": -121.891213729978}, "transactions": [], "price": "$", "location": {"address1": "176 Atlantic Ave", "address2": "", "address3": "", "city": "Pittsburg", "zip_code": "94565", "country": "US", "state": "CA", "display_address": ["176 Atlantic Ave", "Pittsburg, CA 94565"]}, "phone": "+19254271500", "display_phone": "(925) 427-1500", "distance": 3718.5995877940218}, {"id": "8d7A_WtKOQexHxv2gFcMxg", "alias": "las-palmas-pittsburg", "name": "Las Palmas", "image_url": "https://s3-media3.fl.yelpcdn.com/bphoto/4Updi1Zmad0GI5PrU44RpA/o.jpg", "is_closed": false, "url": "https://www.yelp.com/biz/las-palmas-pittsburg?adjust_creative=IokN4du3-7NwKcCaUms5LA&utm_campaign=yelp_api_v3&utm_medium=api_v3_business_search&utm_source=IokN4du3-7NwKcCaUms5LA", "review_count": 7, "categories": [{"alias": "mexican", "title": "Mexican"}, {"alias": "gourmet", "title": "Specialty Food"}], "rating": 2.5, "coordinates": {"latitude": 38.0222937368892, "longitude": -121.887573106986}, "transactions": [], "price": "$", "location": {"address1": "1390 Railroad Ave", "address2": "", "address3": "", "city": "Pittsburg", "zip_code": "94565", "country": "US", "state": "CA", "display_address": ["1390 Railroad Ave", "Pittsburg, CA 94565"]}, "phone": "+19256284323", "display_phone": "(925) 628-4323", "distance": 2029.308932773079}, {"id": "bGoznSfO0E-hjIImnFCqrA", "alias": "pizza-hut-pittsburg-7", "name": "Pizza Hut", "image_url": "https://s3-media2.fl.yelpcdn.com/bphoto/d82LMi2Y2QEGyBp230bhfA/o.jpg", "is_closed": false, "url": "https://www.yelp.com/biz/pizza-hut-pittsburg-7?adjust_creative=IokN4du3-7NwKcCaUms5LA&utm_campaign=yelp_api_v3&utm_medium=api_v3_business_search&utm_source=IokN4du3-7NwKcCaUms5LA", "review_count": 58, "categories": [{"alias": "pizza", "title": "Pizza"}, {"alias": "italian", "title": "Italian"}, {"alias": "chicken_wings", "title": "Chicken Wings"}], "rating": 1.5, "coordinates": {"latitude": 38.0159544324989, "longitude": -121.8903806}, "transactions": [], "price": "$", "location": {"address1": "2110 Railroad Ave", "address2": "Ste 140", "address3": "", "city": "Pittsburg", "zip_code": "94565", "country": "US", "state": "CA", "display_address": ["2110 Railroad Ave", "Ste 140", "Pittsburg, CA 94565"]}, "phone": "+19254391103", "display_phone": "(925) 439-1103", "distance": 2774.2741054119047}, {"id": "p-HJfmaDdRJd4ZwNhgKh4g", "alias": "taco-bell-pittsburg-2", "name": "Taco Bell", "image_url": "https://s3-media3.fl.yelpcdn.com/bphoto/irMdH5d8gZ_q8IPSIyqhrg/o.jpg", "is_closed": false, "url": "https://www.yelp.com/biz/taco-bell-pittsburg-2?adjust_creative=IokN4du3-7NwKcCaUms5LA&utm_campaign=yelp_api_v3&utm_medium=api_v3_business_search&utm_source=IokN4du3-7NwKcCaUms5LA", "review_count": 43, "categories": [{"alias": "hotdogs", "title": "Fast Food"}, {"alias": "tacos", "title": "Tacos"}], "rating": 2.0, "coordinates": {"latitude": 38.0104184726829, "longitude": -121.86943135278}, "transactions": ["delivery"], "price": "$", "location": {"address1": "2111 Loveridge Rd", "address2": "", "address3": "", "city": "Pittsburg", "zip_code": "94565", "country": "US", "state": "CA", "display_address": ["2111 Loveridge Rd", "Pittsburg, CA 94565"]}, "phone": "+19254322873", "display_phone": "(925) 432-2873", "distance": 3451.8159925234295}, {"id": "pHwmKZqUX1xyHDUJt7VOrQ", "alias": "allstar-tamales-san-francisco", "name": "Allstar Tamales", "image_url": "https://s3-media4.fl.yelpcdn.com/bphoto/8y2vDViMY0uFvmH6zgajhg/o.jpg", "is_closed": false, "url": "https://www.yelp.com/biz/allstar-tamales-san-francisco?adjust_creative=IokN4du3-7NwKcCaUms5LA&utm_campaign=yelp_api_v3&utm_medium=api_v3_business_search&utm_source=IokN4du3-7NwKcCaUms5LA", "review_count": 5, "categories": [{"alias": "mexican", "title": "Mexican"}, {"alias": "farmersmarket", "title": "Farmers Market"}], "rating": 4.0, "coordinates": {"latitude": 38.018007, "longitude": -121.882166}, "transactions": [], "price": "$", "location": {"address1": "Various Farmer's Markets", "address2": null, "address3": "", "city": "San Francisco", "zip_code": "94565", "country": "US", "state": "CA", "display_address": ["Various Farmer's Markets", "San Francisco, CA 94565"]}, "phone": "+19252521097", "display_phone": "(925) 252-1097", "distance": 2438.691598793647}, {"id": "PNYVpfelSZbnYjRaI0I0IQ", "alias": "jack-in-the-box-pittsburg", "name": "Jack in the Box", "image_url": "https://s3-media4.fl.yelpcdn.com/bphoto/CTWB-TPvx6Ppans3n_H_QA/o.jpg", "is_closed": false, "url": "https://www.yelp.com/biz/jack-in-the-box-pittsburg?adjust_creative=IokN4du3-7NwKcCaUms5LA&utm_campaign=yelp_api_v3&utm_medium=api_v3_business_search&utm_source=IokN4du3-7NwKcCaUms5LA", "review_count": 28, "categories": [{"alias": "hotdogs", "title": "Fast Food"}, {"alias": "burgers", "title": "Burgers"}, {"alias": "tacos", "title": "Tacos"}], "rating": 2.5, "coordinates": {"latitude": 38.0153569736809, "longitude": -121.889550150835}, "transactions": [], "price": "$", "location": {"address1": "2135 Railroad Ave", "address2": "", "address3": "", "city": "Pittsburg", "zip_code": "94565", "country": "US", "state": "CA", "display_address": ["2135 Railroad Ave", "Pittsburg, CA 94565"]}, "phone": "+19254323378", "display_phone": "(925) 432-3378", "distance": 2819.4311569605684}, {"id": "_wupVl-9AP01OWMkEXlrWg", "alias": "golden-gate-gyro-concord-3", "name": "Golden Gate Gyro", "image_url": "https://s3-media1.fl.yelpcdn.com/bphoto/i8qAuKMQMoCU5SQLIZNLXQ/o.jpg", "is_closed": false, "url": "https://www.yelp.com/biz/golden-gate-gyro-concord-3?adjust_creative=IokN4du3-7NwKcCaUms5LA&utm_campaign=yelp_api_v3&utm_medium=api_v3_business_search&utm_source=IokN4du3-7NwKcCaUms5LA", "review_count": 96, "categories": [{"alias": "foodtrucks", "title": "Food Trucks"}, {"alias": "halal", "title": "Halal"}], "rating": 4.5, "coordinates": {"latitude": 37.9489593505859, "longitude": -122.039596557617}, "transactions": [], "price": "$", "location": {"address1": "", "address2": "", "address3": null, "city": "Concord", "zip_code": "94518", "country": "US", "state": "CA", "display_address": ["Concord, CA 94518"]}, "phone": "+19259995755", "display_phone": "(925) 999-5755", "distance": 16076.816209915462}, {"id": "j4vtxBsVpQ8Y5bgI2Q0bxg", "alias": "ihop-pittsburg-2", "name": "IHOP", "image_url": "https://s3-media2.fl.yelpcdn.com/bphoto/Hjgww8T0wcH4E-0I3-mv9A/o.jpg", "is_closed": false, "url": "https://www.yelp.com/biz/ihop-pittsburg-2?adjust_creative=IokN4du3-7NwKcCaUms5LA&utm_campaign=yelp_api_v3&utm_medium=api_v3_business_search&utm_source=IokN4du3-7NwKcCaUms5LA", "review_count": 116, "categories": [{"alias": "breakfast_brunch", "title": "Breakfast & Brunch"}, {"alias": "tradamerican", "title": "American (Traditional)"}, {"alias": "burgers", "title": "Burgers"}], "rating": 2.0, "coordinates": {"latitude": 38.00864, "longitude": -121.871377288361}, "transactions": ["pickup", "delivery"], "price": "$$", "location": {"address1": "2290 Loveridge Rd", "address2": "", "address3": "", "city": "PITTSBURG", "zip_code": "94565", "country": "US", "state": "CA", "display_address": ["2290 Loveridge Rd", "PITTSBURG, CA 94565"]}, "phone": "+19254276870", "display_phone": "(925) 427-6870", "distance": 3593.999498541711}, {"id": "Cg_VVVVxUrxRUX50gdAWgA", "alias": "wendys-pittsburg", "name": "Wendy's", "image_url": "https://s3-media3.fl.yelpcdn.com/bphoto/G4KBwn-z0p3iMgSb6rp4aw/o.jpg", "is_closed": false, "url": "https://www.yelp.com/biz/wendys-pittsburg?adjust_creative=IokN4du3-7NwKcCaUms5LA&utm_campaign=yelp_api_v3&utm_medium=api_v3_business_search&utm_source=IokN4du3-7NwKcCaUms5LA", "review_count": 30, "categories": [{"alias": "hotdogs", "title": "Fast Food"}, {"alias": "burgers", "title": "Burgers"}], "rating": 2.5, "coordinates": {"latitude": 38.00901, "longitude": -121.87017}, "transactions": ["pickup", "delivery"], "price": "$", "location": {"address1": "2243 Loveridge Road", "address2": "", "address3": "", "city": "Pittsburg", "zip_code": "94565", "country": "US", "state": "CA", "display_address": ["2243 Loveridge Road", "Pittsburg, CA 94565"]}, "phone": "+19254277058", "display_phone": "(925) 427-7058", "distance": 3585.743750555668}, {"id": "qDiQN1peVZLYx0kB3WL6hw", "alias": "dominos-pizza-pittsburg-4", "name": "Domino's Pizza", "image_url": "https://s3-media2.fl.yelpcdn.com/bphoto/Fx7t1y3hYWm3r02t2hYcnA/o.jpg", "is_closed": false, "url": "https://www.yelp.com/biz/dominos-pizza-pittsburg-4?adjust_creative=IokN4du3-7NwKcCaUms5LA&utm_campaign=yelp_api_v3&utm_medium=api_v3_business_search&utm_source=IokN4du3-7NwKcCaUms5LA", "review_count": 98, "categories": [{"alias": "pizza", "title": "Pizza"}, {"alias": "chicken_wings", "title": "Chicken Wings"}, {"alias": "sandwiches", "title": "Sandwiches"}], "rating": 2.5, "coordinates": {"latitude": 38.0084086026815, "longitude": -121.886859412089}, "transactions": [], "price": "$", "location": {"address1": "2931 Harbor St", "address2": "Ste K", "address3": "", "city": "Pittsburg", "zip_code": "94565", "country": "US", "state": "CA", "display_address": ["2931 Harbor St", "Ste K", "Pittsburg, CA 94565"]}, "phone": "+19254273030", "display_phone": "(925) 427-3030", "distance": 3535.258964224754}, {"id": "nu-NKEZsSFP-FuOrFIZ4hQ", "alias": "burger-king-pittsburg-6", "name": "Burger King", "image_url": "https://s3-media3.fl.yelpcdn.com/bphoto/61Ue6cUJB4PtDQtZA-mbSw/o.jpg", "is_closed": false, "url": "https://www.yelp.com/biz/burger-king-pittsburg-6?adjust_creative=IokN4du3-7NwKcCaUms5LA&utm_campaign=yelp_api_v3&utm_medium=api_v3_business_search&utm_source=IokN4du3-7NwKcCaUms5LA", "review_count": 25, "categories": [{"alias": "burgers", "title": "Burgers"}, {"alias": "hotdogs", "title": "Fast Food"}], "rating": 1.5, "coordinates": {"latitude": 38.014324, "longitude": -121.891071}, "transactions": [], "price": "$", "location": {"address1": "2162 RailRd Ave", "address2": "", "address3": "", "city": "Pittsburg", "zip_code": "94565", "country": "US", "state": "CA", "display_address": ["2162 RailRd Ave", "Pittsburg, CA 94565"]}, "phone": "+12093585830", "display_phone": "(209) 358-5830", "distance": 2962.091853317064}, {"id": "r95IMO6Edj9JUV-GkZ4fxw", "alias": "subway-restaurants-pittsburg-4", "name": "Subway Restaurants", "image_url": "https://s3-media2.fl.yelpcdn.com/bphoto/XudD4zY2pkxNRE9sph-vRg/o.jpg", "is_closed": false, "url": "https://www.yelp.com/biz/subway-restaurants-pittsburg-4?adjust_creative=IokN4du3-7NwKcCaUms5LA&utm_campaign=yelp_api_v3&utm_medium=api_v3_business_search&utm_source=IokN4du3-7NwKcCaUms5LA", "review_count": 12, "categories": [{"alias": "sandwiches", "title": "Sandwiches"}], "rating": 2.5, "coordinates": {"latitude": 38.0106142247249, "longitude": -121.869310308696}, "transactions": [], "price": "$", "location": {"address1": "2121 Loveridge Rd", "address2": "", "address3": "", "city": "Pittsburg", "zip_code": "94565", "country": "US", "state": "CA", "display_address": ["2121 Loveridge Rd", "Pittsburg, CA 94565"]}, "phone": "+19254320847", "display_phone": "(925) 432-0847", "distance": 3457.9987559796423}, {"id": "7LYlcaS2860zMjUOJyJ48Q", "alias": "the-small-world-cafe-pittsburg", "name": "The Small World Cafe", "image_url": "", "is_closed": false, "url": "https://www.yelp.com/biz/the-small-world-cafe-pittsburg?adjust_creative=IokN4du3-7NwKcCaUms5LA&utm_campaign=yelp_api_v3&utm_medium=api_v3_business_search&utm_source=IokN4du3-7NwKcCaUms5LA", "review_count": 1, "categories": [{"alias": "delis", "title": "Delis"}], "rating": 4.0, "coordinates": {"latitude": 38.0082389, "longitude": -121.8672282}, "transactions": [], "location": {"address1": "1409 E Leland Rd", "address2": "", "address3": "", "city": "Pittsburg", "zip_code": "94565", "country": "US", "state": "CA", "display_address": ["1409 E Leland Rd", "Pittsburg, CA 94565"]}, "phone": "", "display_phone": "", "distance": 3737.1425274745075}, {"id": "Lv6OZs-7WSe46aJWVJPHUg", "alias": "la-aurora-market-pittsburg", "name": "La Aurora Market", "image_url": "https://s3-media2.fl.yelpcdn.com/bphoto/qc7013iNZIWcltAQKix-Qw/o.jpg", "is_closed": false, "url": "https://www.yelp.com/biz/la-aurora-market-pittsburg?adjust_creative=IokN4du3-7NwKcCaUms5LA&utm_campaign=yelp_api_v3&utm_medium=api_v3_business_search&utm_source=IokN4du3-7NwKcCaUms5LA", "review_count": 2, "categories": [{"alias": "sandwiches", "title": "Sandwiches"}], "rating": 1.5, "coordinates": {"latitude": 38.02937, "longitude": -121.88992}, "transactions": [], "location": {"address1": "290 W 10th St", "address2": "", "address3": "", "city": "Pittsburg", "zip_code": "94565", "country": "US", "state": "CA", "display_address": ["290 W 10th St", "Pittsburg, CA 94565"]}, "phone": "+19254392323", "display_phone": "(925) 439-2323", "distance": 1390.0643643653648}, {"id": "JlwCY-qYhcuV6vftiEJnbQ", "alias": "mcdonalds-pittsburg-2", "name": "McDonald's", "image_url": "https://s3-media2.fl.yelpcdn.com/bphoto/9Fk7TdHBnnL4L0i0xAyqjA/o.jpg", "is_closed": false, "url": "https://www.yelp.com/biz/mcdonalds-pittsburg-2?adjust_creative=IokN4du3-7NwKcCaUms5LA&utm_campaign=yelp_api_v3&utm_medium=api_v3_business_search&utm_source=IokN4du3-7NwKcCaUms5LA", "review_count": 58, "categories": [{"alias": "hotdogs", "title": "Fast Food"}, {"alias": "burgers", "title": "Burgers"}, {"alias": "coffee", "title": "Coffee & Tea"}], "rating": 2.0, "coordinates": {"latitude": 38.0079923732697, "longitude": -121.887360561436}, "transactions": [], "price": "$", "location": {"address1": "460 Atlantic Ave", "address2": "", "address3": "", "city": "Pittsburg", "zip_code": "94565", "country": "US", "state": "CA", "display_address": ["460 Atlantic Ave", "Pittsburg, CA 94565"]}, "phone": "+19254324081", "display_phone": "(925) 432-4081", "distance": 3587.0287220247383}, {"id": "aYJ6AeaypShATxgDTWij6g", "alias": "subway-restaurants-pittsburg-2", "name": "Subway Restaurants", "image_url": "https://s3-media4.fl.yelpcdn.com/bphoto/gjylT5FRjJVmE7VVj3IDog/o.jpg", "is_closed": false, "url": "https://www.yelp.com/biz/subway-restaurants-pittsburg-2?adjust_creative=IokN4du3-7NwKcCaUms5LA&utm_campaign=yelp_api_v3&utm_medium=api_v3_business_search&utm_source=IokN4du3-7NwKcCaUms5LA", "review_count": 4, "categories": [{"alias": "sandwiches", "title": "Sandwiches"}], "rating": 2.5, "coordinates": {"latitude": 38.0081424, "longitude": -121.8918469}, "transactions": [], "price": "$", "location": {"address1": "139 Atlantic Ave", "address2": null, "address3": null, "city": "Pittsburg", "zip_code": "94565", "country": "US", "state": "CA", "display_address": ["139 Atlantic Ave", "Pittsburg, CA 94565"]}, "phone": "+19254398000", "display_phone": "(925) 439-8000", "distance": 3616.1743162976045}, {"id": "OF-1joHm4X7p2WVKhJzseg", "alias": "jack-in-the-box-pittsburg-3", "name": "Jack in the Box", "image_url": "https://s3-media3.fl.yelpcdn.com/bphoto/R7j_S8rHz42Aybz_JGcrzw/o.jpg", "is_closed": false, "url": "https://www.yelp.com/biz/jack-in-the-box-pittsburg-3?adjust_creative=IokN4du3-7NwKcCaUms5LA&utm_campaign=yelp_api_v3&utm_medium=api_v3_business_search&utm_source=IokN4du3-7NwKcCaUms5LA", "review_count": 27, "categories": [{"alias": "hotdogs", "title": "Fast Food"}, {"alias": "burgers", "title": "Burgers"}, {"alias": "tacos", "title": "Tacos"}], "rating": 3.0, "coordinates": {"latitude": 38.0134301, "longitude": -121.869522035122}, "transactions": [], "price": "$", "location": {"address1": "1213 California Ave", "address2": "", "address3": "", "city": "Pittsburg", "zip_code": "94565", "country": "US", "state": "CA", "display_address": ["1213 California Ave", "Pittsburg, CA 94565"]}, "phone": "+19254320184", "display_phone": "(925) 432-0184", "distance": 3132.4168338785066}, {"id": "gZirC8xhYEmLB8QwbILJWQ", "alias": "leonardis-pizza-pittsburg", "name": "Leonardi's Pizza", "image_url": "", "is_closed": false, "url": "https://www.yelp.com/biz/leonardis-pizza-pittsburg?adjust_creative=IokN4du3-7NwKcCaUms5LA&utm_campaign=yelp_api_v3&utm_medium=api_v3_business_search&utm_source=IokN4du3-7NwKcCaUms5LA", "review_count": 2, "categories": [{"alias": "pizza", "title": "Pizza"}], "rating": 3.0, "coordinates": {"latitude": 38.0114290195256, "longitude": -121.857596933842}, "transactions": [], "price": "$", "location": {"address1": "2400 N Park Blvd", "address2": "", "address3": "WinCo Foods", "city": "Pittsburg", "zip_code": "94565", "country": "US", "state": "CA", "display_address": ["2400 N Park Blvd", "WinCo Foods", "Pittsburg, CA 94565"]}, "phone": "+19254398505", "display_phone": "(925) 439-8505", "distance": 3805.41588498447}, {"id": "RNH5_WlQv27DQ9pIOtPh6Q", "alias": "la-sierra-pittsburg", "name": "La Sierra", "image_url": "", "is_closed": false, "url": "https://www.yelp.com/biz/la-sierra-pittsburg?adjust_creative=IokN4du3-7NwKcCaUms5LA&utm_campaign=yelp_api_v3&utm_medium=api_v3_business_search&utm_source=IokN4du3-7NwKcCaUms5LA", "review_count": 1, "categories": [{"alias": "restaurants", "title": "Restaurants"}], "rating": 2.0, "coordinates": {"latitude": 38.02772, "longitude": -121.8832}, "transactions": [], "price": "$", "location": {"address1": "295 E 10th St", "address2": "", "address3": "", "city": "Pittsburg", "zip_code": "94565", "country": "US", "state": "CA", "display_address": ["295 E 10th St", "Pittsburg, CA 94565"]}, "phone": "+19254274797", "display_phone": "(925) 427-4797", "distance": 1394.1286064142328}, {"id": "GqaM_gE2f9fT9be16lWPag", "alias": "subway-pittsburg-3", "name": "Subway", "image_url": "https://s3-media3.fl.yelpcdn.com/bphoto/wAA74o-LvFgLyzs9tkQr9g/o.jpg", "is_closed": false, "url": "https://www.yelp.com/biz/subway-pittsburg-3?adjust_creative=IokN4du3-7NwKcCaUms5LA&utm_campaign=yelp_api_v3&utm_medium=api_v3_business_search&utm_source=IokN4du3-7NwKcCaUms5LA", "review_count": 14, "categories": [{"alias": "sandwiches", "title": "Sandwiches"}, {"alias": "hotdogs", "title": "Fast Food"}], "rating": 2.5, "coordinates": {"latitude": 38.0083028832712, "longitude": -121.891647577286}, "transactions": [], "price": "$", "location": {"address1": "2965 Railroad Ave", "address2": "", "address3": "", "city": "Pittsburg", "zip_code": "94565", "country": "US", "state": "CA", "display_address": ["2965 Railroad Ave", "Pittsburg, CA 94565"]}, "phone": "", "display_phone": "", "distance": 3624.9416197221276}, {"id": "FXK3GYq0uP5zv49c6uZ-xQ", "alias": "viva-mexico-pittsburg", "name": "Viva Mexico", "image_url": "", "is_closed": false, "url": "https://www.yelp.com/biz/viva-mexico-pittsburg?adjust_creative=IokN4du3-7NwKcCaUms5LA&utm_campaign=yelp_api_v3&utm_medium=api_v3_business_search&utm_source=IokN4du3-7NwKcCaUms5LA", "review_count": 7, "categories": [{"alias": "mexican", "title": "Mexican"}], "rating": 3.0, "coordinates": {"latitude": 38.0081579, "longitude": -121.891904}, "transactions": [], "price": "$$", "location": {"address1": "149 Atlantic Ave", "address2": "", "address3": "", "city": "Pittsburg", "zip_code": "94565", "country": "US", "state": "CA", "display_address": ["149 Atlantic Ave", "Pittsburg, CA 94565"]}, "phone": "+19254279133", "display_phone": "(925) 427-9133", "distance": 3620.6770041187674}, {"id": "xomxVUXe8Sy5R2nt7qBxxg", "alias": "fired-mobile-pizza-oven-stockton", "name": "FIRED Mobile Pizza Oven", "image_url": "https://s3-media4.fl.yelpcdn.com/bphoto/JV4MGBFFrJGZQbmtdoOLFQ/o.jpg", "is_closed": false, "url": "https://www.yelp.com/biz/fired-mobile-pizza-oven-stockton?adjust_creative=IokN4du3-7NwKcCaUms5LA&utm_campaign=yelp_api_v3&utm_medium=api_v3_business_search&utm_source=IokN4du3-7NwKcCaUms5LA", "review_count": 8, "categories": [{"alias": "pizza", "title": "Pizza"}, {"alias": "catering", "title": "Caterers"}, {"alias": "foodtrucks", "title": "Food Trucks"}], "rating": 5.0, "coordinates": {"latitude": 38.0521138, "longitude": -121.3484448}, "transactions": [], "location": {"address1": null, "address2": null, "address3": "", "city": "Stockton", "zip_code": "95209", "country": "US", "state": "CA", "display_address": ["Stockton, CA 95209"]}, "phone": "+12092424105", "display_phone": "(209) 242-4105", "distance": 46710.02647019959}, {"id": "Ig_6H85ZlMy_j4CVTw357Q", "alias": "mcdonalds-pittsburg-4", "name": "McDonald's", "image_url": "https://s3-media2.fl.yelpcdn.com/bphoto/ifBI6XG6fwFla3wI2h56aA/o.jpg", "is_closed": false, "url": "https://www.yelp.com/biz/mcdonalds-pittsburg-4?adjust_creative=IokN4du3-7NwKcCaUms5LA&utm_campaign=yelp_api_v3&utm_medium=api_v3_business_search&utm_source=IokN4du3-7NwKcCaUms5LA", "review_count": 4, "categories": [{"alias": "hotdogs", "title": "Fast Food"}, {"alias": "burgers", "title": "Burgers"}, {"alias": "coffee", "title": "Coffee & Tea"}], "rating": 1.0, "coordinates": {"latitude": 38.009338, "longitude": -121.8685736}, "transactions": [], "price": "$", "location": {"address1": "2203 Loveridge Ln", "address2": null, "address3": null, "city": "Pittsburg", "zip_code": "94565", "country": "US", "state": "CA", "display_address": ["2203 Loveridge Ln", "Pittsburg, CA 94565"]}, "phone": "+19254395289", "display_phone": "(925) 439-5289", "distance": 3589.4880466198765}, {"id": "CUwBAy6lrFi4x6Neu9eRVw", "alias": "mini-street-burger-alameda-3", "name": "Mini Street Burger", "image_url": "https://s3-media2.fl.yelpcdn.com/bphoto/Kh-OQKBIclWY1dCeIuu57w/o.jpg", "is_closed": false, "url": "https://www.yelp.com/biz/mini-street-burger-alameda-3?adjust_creative=IokN4du3-7NwKcCaUms5LA&utm_campaign=yelp_api_v3&utm_medium=api_v3_business_search&utm_source=IokN4du3-7NwKcCaUms5LA", "review_count": 28, "categories": [{"alias": "foodtrucks", "title": "Food Trucks"}, {"alias": "burgers", "title": "Burgers"}], "rating": 4.0, "coordinates": {"latitude": 37.82628, "longitude": -122.25101}, "transactions": [], "location": {"address1": null, "address2": null, "address3": null, "city": "Alameda", "zip_code": "94611", "country": "US", "state": "CA", "display_address": ["Alameda, CA 94611"]}, "phone": "+15108278982", "display_phone": "(510) 827-8982", "distance": 36337.90990582246}, {"id": "7hoR85ZbJVRQ98Q14OlQZQ", "alias": "cosa-nostra-pasta-truck-berkeley", "name": "Cosa Nostra Pasta Truck", "image_url": "https://s3-media1.fl.yelpcdn.com/bphoto/kJNRKi9NzgsPf3KmTr_fAg/o.jpg", "is_closed": false, "url": "https://www.yelp.com/biz/cosa-nostra-pasta-truck-berkeley?adjust_creative=IokN4du3-7NwKcCaUms5LA&utm_campaign=yelp_api_v3&utm_medium=api_v3_business_search&utm_source=IokN4du3-7NwKcCaUms5LA", "review_count": 31, "categories": [{"alias": "foodtrucks", "title": "Food Trucks"}, {"alias": "italian", "title": "Italian"}], "rating": 5.0, "coordinates": {"latitude": 37.8760173212886, "longitude": -122.303487025201}, "transactions": [], "price": "$$", "location": {"address1": "701 Page St", "address2": null, "address3": null, "city": "Berkeley", "zip_code": "94710", "country": "US", "state": "CA", "display_address": ["701 Page St", "Berkeley, CA 94710"]}, "phone": "+15102448782", "display_phone": "(510) 244-8782", "distance": 41232.05693329892}, {"id": "DC42MrpWtqEeWRmMsn6Z8w", "alias": "the-everest-momo-fremont-2", "name": "The Everest Momo", "image_url": "https://s3-media2.fl.yelpcdn.com/bphoto/T2f7tUQ1c104otx9oSdqYw/o.jpg", "is_closed": false, "url": "https://www.yelp.com/biz/the-everest-momo-fremont-2?adjust_creative=IokN4du3-7NwKcCaUms5LA&utm_campaign=yelp_api_v3&utm_medium=api_v3_business_search&utm_source=IokN4du3-7NwKcCaUms5LA", "review_count": 23, "categories": [{"alias": "foodtrucks", "title": "Food Trucks"}, {"alias": "indpak", "title": "Indian"}, {"alias": "himalayan", "title": "Himalayan/Nepalese"}], "rating": 4.5, "coordinates": {"latitude": 37.54643, "longitude": -121.98512}, "transactions": [], "price": "$", "location": {"address1": "39233 Fremont Blvd", "address2": null, "address3": null, "city": "Fremont", "zip_code": "94538", "country": "US", "state": "CA", "display_address": ["39233 Fremont Blvd", "Fremont, CA 94538"]}, "phone": "+14088406369", "display_phone": "(408) 840-6369", "distance": 55612.56979705362}, {"id": "jCcAuXhCpeJP2n-8ol7mxg", "alias": "kolobok-russian-soul-food-truck-oakland", "name": "Kolobok Russian Soul Food Truck", "image_url": "https://s3-media1.fl.yelpcdn.com/bphoto/k8s1Bfc05Iw7SJXE6VJ74Q/o.jpg", "is_closed": false, "url": "https://www.yelp.com/biz/kolobok-russian-soul-food-truck-oakland?adjust_creative=IokN4du3-7NwKcCaUms5LA&utm_campaign=yelp_api_v3&utm_medium=api_v3_business_search&utm_source=IokN4du3-7NwKcCaUms5LA", "review_count": 47, "categories": [{"alias": "foodtrucks", "title": "Food Trucks"}, {"alias": "russian", "title": "Russian"}], "rating": 4.5, "coordinates": {"latitude": 37.7883087690458, "longitude": -122.309032460882}, "transactions": [], "price": "$$", "location": {"address1": null, "address2": null, "address3": "", "city": "Oakland", "zip_code": "94577", "country": "US", "state": "CA", "display_address": ["Oakland, CA 94577"]}, "phone": "+15105996542", "display_phone": "(510) 599-6542", "distance": 46782.38734340361}, {"id": "rM6pPB_qmQ3de5yGpfLT1g", "alias": "lomo-libre-san-francisco-2", "name": "Lomo Libre", "image_url": "https://s3-media1.fl.yelpcdn.com/bphoto/vjnO-EUjFHKoLMy2_JQYvg/o.jpg", "is_closed": false, "url": "https://www.yelp.com/biz/lomo-libre-san-francisco-2?adjust_creative=IokN4du3-7NwKcCaUms5LA&utm_campaign=yelp_api_v3&utm_medium=api_v3_business_search&utm_source=IokN4du3-7NwKcCaUms5LA", "review_count": 8, "categories": [{"alias": "foodtrucks", "title": "Food Trucks"}, {"alias": "peruvian", "title": "Peruvian"}], "rating": 5.0, "coordinates": {"latitude": 37.799634, "longitude": -122.436301}, "transactions": [], "location": {"address1": "2101 Lombard St", "address2": "", "address3": null, "city": "San Francisco", "zip_code": "94123", "country": "US", "state": "CA", "display_address": ["2101 Lombard St", "San Francisco, CA 94123"]}, "phone": "+14156198149", "display_phone": "(415) 619-8149", "distance": 55508.64650399932}, {"id": "lgheXsHqe66AEZwoPDIEpw", "alias": "taco-coma-newark", "name": "Taco Coma", "image_url": "https://s3-media3.fl.yelpcdn.com/bphoto/DDz5lZDL5lDiRR_Ph0L4Sg/o.jpg", "is_closed": false, "url": "https://www.yelp.com/biz/taco-coma-newark?adjust_creative=IokN4du3-7NwKcCaUms5LA&utm_campaign=yelp_api_v3&utm_medium=api_v3_business_search&utm_source=IokN4du3-7NwKcCaUms5LA", "review_count": 3, "categories": [{"alias": "foodstands", "title": "Food Stands"}, {"alias": "tacos", "title": "Tacos"}], "rating": 5.0, "coordinates": {"latitude": 37.53453, "longitude": -122.03284}, "transactions": [], "location": {"address1": "", "address2": null, "address3": "", "city": "Newark", "zip_code": "94560", "country": "US", "state": "CA", "display_address": ["Newark, CA 94560"]}, "phone": "+15106971448", "display_phone": "(510) 697-1448", "distance": 58354.04280609185}, {"id": "uuouQQIFQ1B9mkmcxaAKFA", "alias": "tacos-el-rey-oakland", "name": "Tacos El Rey", "image_url": "https://s3-media2.fl.yelpcdn.com/bphoto/DblyFrtT9uyPCQAUfPbYbQ/o.jpg", "is_closed": false, "url": "https://www.yelp.com/biz/tacos-el-rey-oakland?adjust_creative=IokN4du3-7NwKcCaUms5LA&utm_campaign=yelp_api_v3&utm_medium=api_v3_business_search&utm_source=IokN4du3-7NwKcCaUms5LA", "review_count": 9, "categories": [{"alias": "foodtrucks", "title": "Food Trucks"}, {"alias": "mexican", "title": "Mexican"}], "rating": 4.0, "coordinates": {"latitude": 37.8294034, "longitude": -122.2875758}, "transactions": [], "price": "$", "location": {"address1": "40th & Horton", "address2": "", "address3": null, "city": "Oakland", "zip_code": "94608", "country": "US", "state": "CA", "display_address": ["40th & Horton", "Oakland, CA 94608"]}, "phone": "+15108130232", "display_phone": "(510) 813-0232", "distance": 42608.188734905605}, {"id": "i6ZwMjYIbmFZ8EGYz6x5Bw", "alias": "phat-salads-and-wraps-napa", "name": "Phat Salads and Wraps", "image_url": "https://s3-media2.fl.yelpcdn.com/bphoto/FbrUwtrVIx2cLXiPdBhHkw/o.jpg", "is_closed": false, "url": "https://www.yelp.com/biz/phat-salads-and-wraps-napa?adjust_creative=IokN4du3-7NwKcCaUms5LA&utm_campaign=yelp_api_v3&utm_medium=api_v3_business_search&utm_source=IokN4du3-7NwKcCaUms5LA", "review_count": 48, "categories": [{"alias": "foodtrucks", "title": "Food Trucks"}, {"alias": "wraps", "title": "Wraps"}], "rating": 4.0, "coordinates": {"latitude": 38.3234491, "longitude": -122.3023962}, "transactions": [], "price": "$", "location": {"address1": "", "address2": "", "address3": "", "city": "Napa", "zip_code": "94558", "country": "US", "state": "CA", "display_address": ["Napa, CA 94558"]}, "phone": "+17073639658", "display_phone": "(707) 363-9658", "distance": 48439.08721219751}, {"id": "sR0Wy3LYGdYV9HLszRlMmw", "alias": "tacos-la-palmita-stockton", "name": "Tacos La Palmita", "image_url": "https://s3-media2.fl.yelpcdn.com/bphoto/pzYoRmZjUQqxZ7qOyU7hUQ/o.jpg", "is_closed": false, "url": "https://www.yelp.com/biz/tacos-la-palmita-stockton?adjust_creative=IokN4du3-7NwKcCaUms5LA&utm_campaign=yelp_api_v3&utm_medium=api_v3_business_search&utm_source=IokN4du3-7NwKcCaUms5LA", "review_count": 90, "categories": [{"alias": "tacos", "title": "Tacos"}, {"alias": "foodtrucks", "title": "Food Trucks"}], "rating": 4.5, "coordinates": {"latitude": 38.008129, "longitude": -121.320219}, "transactions": ["pickup", "delivery"], "price": "$", "location": {"address1": "6393 Pacific Ave", "address2": null, "address3": null, "city": "Stockton", "zip_code": "95207", "country": "US", "state": "CA", "display_address": ["6393 Pacific Ave", "Stockton, CA 95207"]}, "phone": "+12093026825", "display_phone": "(209) 302-6825", "distance": 49303.81794607016}, {"id": "SbjAjfh2riT7rWxo2OITJA", "alias": "candies-kitchen-sacramento", "name": "Candies Kitchen", "image_url": "https://s3-media1.fl.yelpcdn.com/bphoto/wZehoZn9-gQLuWPX4QIOLA/o.jpg", "is_closed": false, "url": "https://www.yelp.com/biz/candies-kitchen-sacramento?adjust_creative=IokN4du3-7NwKcCaUms5LA&utm_campaign=yelp_api_v3&utm_medium=api_v3_business_search&utm_source=IokN4du3-7NwKcCaUms5LA", "review_count": 2, "categories": [{"alias": "cajun", "title": "Cajun/Creole"}, {"alias": "soulfood", "title": "Soul Food"}, {"alias": "foodtrucks", "title": "Food Trucks"}], "rating": 3.5, "coordinates": {"latitude": 38.59429, "longitude": -121.48536}, "transactions": [], "location": {"address1": "1100 Richards Blvd", "address2": null, "address3": "", "city": "Sacramento", "zip_code": "95811", "country": "US", "state": "CA", "display_address": ["1100 Richards Blvd", "Sacramento, CA 95811"]}, "phone": "+19164399922", "display_phone": "(916) 439-9922", "distance": 70685.7781489101}, {"id": "4HaUjRfwmHUOoFAeKi84dw", "alias": "mudville-mcs-stockton", "name": "Mudville Mc's", "image_url": "https://s3-media4.fl.yelpcdn.com/bphoto/yOlLV3w6yY7iPmRFJQbA5A/o.jpg", "is_closed": false, "url": "https://www.yelp.com/biz/mudville-mcs-stockton?adjust_creative=IokN4du3-7NwKcCaUms5LA&utm_campaign=yelp_api_v3&utm_medium=api_v3_business_search&utm_source=IokN4du3-7NwKcCaUms5LA", "review_count": 3, "categories": [{"alias": "foodtrucks", "title": "Food Trucks"}, {"alias": "soulfood", "title": "Soul Food"}, {"alias": "spanish", "title": "Spanish"}], "rating": 3.0, "coordinates": {"latitude": 37.9772033691406, "longitude": -121.298080444336}, "transactions": [], "location": {"address1": "", "address2": "", "address3": "", "city": "Stockton", "zip_code": "95204", "country": "US", "state": "CA", "display_address": ["Stockton, CA 95204"]}, "phone": "+16572294627", "display_phone": "(657) 229-4627", "distance": 49289.33675905972}, {"id": "Mij1ZvLLpqvNmJFWNz9IsQ", "alias": "paquitas-mexican-grill-sacramento-2", "name": "Paquitas Mexican Grill", "image_url": "https://s3-media2.fl.yelpcdn.com/bphoto/Onav96dKMe8cWeFXMNFcyQ/o.jpg", "is_closed": false, "url": "https://www.yelp.com/biz/paquitas-mexican-grill-sacramento-2?adjust_creative=IokN4du3-7NwKcCaUms5LA&utm_campaign=yelp_api_v3&utm_medium=api_v3_business_search&utm_source=IokN4du3-7NwKcCaUms5LA", "review_count": 73, "categories": [{"alias": "foodtrucks", "title": "Food Trucks"}, {"alias": "mexican", "title": "Mexican"}], "rating": 4.0, "coordinates": {"latitude": 38.549732, "longitude": -121.406281}, "transactions": [], "price": "$", "location": {"address1": "49 Bicentennial Cir", "address2": null, "address3": "", "city": "Sacramento", "zip_code": "95826", "country": "US", "state": "CA", "display_address": ["49 Bicentennial Cir", "Sacramento, CA 95826"]}, "phone": "+15308484666", "display_phone": "(530) 848-4666", "distance": 70244.44006789588}, {"id": "8SNGFcMWZkvS4GWDUL8w1Q", "alias": "noon-o-kabob-san-jose-4", "name": "Noon O Kabob", "image_url": "https://s3-media2.fl.yelpcdn.com/bphoto/5GmY5FRw0m0XEWC5XXbVlA/o.jpg", "is_closed": false, "url": "https://www.yelp.com/biz/noon-o-kabob-san-jose-4?adjust_creative=IokN4du3-7NwKcCaUms5LA&utm_campaign=yelp_api_v3&utm_medium=api_v3_business_search&utm_source=IokN4du3-7NwKcCaUms5LA", "review_count": 29, "categories": [{"alias": "foodtrucks", "title": "Food Trucks"}, {"alias": "kebab", "title": "Kebab"}, {"alias": "persian", "title": "Persian/Iranian"}], "rating": 4.5, "coordinates": {"latitude": 37.3940232, "longitude": -122.0288052}, "transactions": [], "price": "$$", "location": {"address1": null, "address2": null, "address3": null, "city": "San Jose", "zip_code": "95101", "country": "US", "state": "CA", "display_address": ["San Jose, CA 95101"]}, "phone": "+14083346777", "display_phone": "(408) 334-6777", "distance": 72979.20659678687}, {"id": "XTJJ_PUQoJKIh31ZIzsFzw", "alias": "cochinita-food-truck-san-francisco-6", "name": "Cochinita Food Truck", "image_url": "https://s3-media2.fl.yelpcdn.com/bphoto/w77SOd2jVJjOh1lwuYQ42w/o.jpg", "is_closed": false, "url": "https://www.yelp.com/biz/cochinita-food-truck-san-francisco-6?adjust_creative=IokN4du3-7NwKcCaUms5LA&utm_campaign=yelp_api_v3&utm_medium=api_v3_business_search&utm_source=IokN4du3-7NwKcCaUms5LA", "review_count": 49, "categories": [{"alias": "foodtrucks", "title": "Food Trucks"}, {"alias": "mexican", "title": "Mexican"}], "rating": 4.5, "coordinates": {"latitude": 37.770753, "longitude": -122.3916722}, "transactions": [], "price": "$", "location": {"address1": "601 Mission Blvd N", "address2": null, "address3": "", "city": "San Francisco", "zip_code": "94103", "country": "US", "state": "CA", "display_address": ["601 Mission Blvd N", "San Francisco, CA 94103"]}, "phone": "+14159883663", "display_phone": "(415) 988-3663", "distance": 53835.77332170871}, {"id": "kN2Q5z0kFXSyyVht1_jETA", "alias": "che-buono-sacramento-4", "name": "Che Buono", "image_url": "https://s3-media1.fl.yelpcdn.com/bphoto/LnHfAM-V8S9jM6s_rOFkQA/o.jpg", "is_closed": false, "url": "https://www.yelp.com/biz/che-buono-sacramento-4?adjust_creative=IokN4du3-7NwKcCaUms5LA&utm_campaign=yelp_api_v3&utm_medium=api_v3_business_search&utm_source=IokN4du3-7NwKcCaUms5LA", "review_count": 46, "categories": [{"alias": "foodtrucks", "title": "Food Trucks"}, {"alias": "italian", "title": "Italian"}, {"alias": "pizza", "title": "Pizza"}], "rating": 4.5, "coordinates": {"latitude": 38.5815719, "longitude": -121.4943996}, "transactions": [], "price": "$$", "location": {"address1": "", "address2": null, "address3": "", "city": "Sacramento", "zip_code": "95811", "country": "US", "state": "CA", "display_address": ["Sacramento, CA 95811"]}, "phone": "+19164306663", "display_phone": "(916) 430-6663", "distance": 69056.68265167566}, {"id": "7ETh5878KSnGQnLxLE_yaQ", "alias": "gyrostop-sacramento", "name": "GyroStop", "image_url": "https://s3-media1.fl.yelpcdn.com/bphoto/xQsct4YKnW0qSJOmK_gsxw/o.jpg", "is_closed": false, "url": "https://www.yelp.com/biz/gyrostop-sacramento?adjust_creative=IokN4du3-7NwKcCaUms5LA&utm_campaign=yelp_api_v3&utm_medium=api_v3_business_search&utm_source=IokN4du3-7NwKcCaUms5LA", "review_count": 74, "categories": [{"alias": "mediterranean", "title": "Mediterranean"}, {"alias": "foodtrucks", "title": "Food Trucks"}], "rating": 4.0, "coordinates": {"latitude": 38.6621589660645, "longitude": -121.336738586426}, "transactions": [], "price": "$$", "location": {"address1": "", "address2": "", "address3": "", "city": "Sacramento", "zip_code": "95841", "country": "US", "state": "CA", "display_address": ["Sacramento, CA 95841"]}, "phone": "+19163044976", "display_phone": "(916) 304-4976", "distance": 83294.50654500499}, {"id": "C9uewBH5505NV0EWYBIJAA", "alias": "lady-and-l-aperitivo-san-jose", "name": "Lady & L'Aperitivo", "image_url": "https://s3-media4.fl.yelpcdn.com/bphoto/3nz0sRE9MlOq_4xVRQRt9w/o.jpg", "is_closed": false, "url": "https://www.yelp.com/biz/lady-and-l-aperitivo-san-jose?adjust_creative=IokN4du3-7NwKcCaUms5LA&utm_campaign=yelp_api_v3&utm_medium=api_v3_business_search&utm_source=IokN4du3-7NwKcCaUms5LA", "review_count": 1, "categories": [{"alias": "bakeries", "title": "Bakeries"}, {"alias": "desserts", "title": "Desserts"}, {"alias": "cheesesteaks", "title": "Cheesesteaks"}], "rating": 5.0, "coordinates": {"latitude": 37.2208938598633, "longitude": -121.861633300781}, "transactions": [], "location": {"address1": null, "address2": null, "address3": "", "city": "San Jose", "zip_code": "95120", "country": "US", "state": "CA", "display_address": ["San Jose, CA 95120"]}, "phone": "", "display_phone": "", "distance": 96819.76969192663}]}